Workbook

Sheet Start Here
B5: Pathway-Mapping Tool (draft prototype)
B6: Map industry competencies to education, assign partner roles, find duplication and gaps, and open multiple entry points into technician careers.
B8: The five steps
B9: Step | C9: What you do | D9: Worksheet | E9: How
B10: 1 | C10: Define the roles | D10: 1 Roles | E10: Name the role families employers hire for, with O*NET/CIP codes and day-one, year-one, year-three tasks.
B11: 2 | C11: Map competencies to education | D11: 2 Competency Spine | E11: One row per competency. Set the depth each role needs (Core / Working / Aware) and where each is taught: high school, community college, university, industry credential, non-credit or apprenticeship.
B12: 3 | C12: Assign partner roles | D12: 3 Partner Roles | E12: Mark who Leads (L) and who Supports (S) each function. The sheet flags functions with no lead or more than one.
B13: 4 | C13: Find overlaps and gaps | D13: 4 Overlap and Gaps | E13: Flags are calculated from the spine. For each “Check” row, answer the three questions: same audience, same depth, same credential?
B14: 5 | C14: Open multiple entry points | D14: 5 Entry Points | E14: List the stops (credentials with job value) and the doors onto them, with how credit connects.
B16: Then check the Summary sheet for counts of gaps, overlaps, and partner functions without a lead.
B18: How to read the colors
C19: Your input
C20: Calculated from other sheets; don’t type here
B22: Adapting the tool to another sector
B23: 1. | C23: Rename the five role families on “1 Roles”; the spine and summary column headers update automatically.
B24: 2. | C24: Replace the rows on “2 Competency Spine” with your sector’s competencies (keep the column layout). Relabel the “where taught” columns if your layers differ.
B25: 3. | C25: Keep course codes in one cell per layer, separated by “ / ” (for example, ABC101 / ABC205). The overlap check counts them.
B26: 4. | C26: Overwrite the Arizona example entries on sheets 3 and 5 with your own partners and doors.
B28: Source of the starter competency spine
B29: Seeded from the SciTech Institute Semiconductor Manufacturing Skills Crosswalk (full copy on the “Source Crosswalk” sheet): 6 core, 11 cluster, and 73 pathway competencies across five O*NET role families. Core rows combine the source’s multi-row entries; course codes and standards are carried over as written.
B31: SP-ATE: Semiconductor Pathways in Arizona’s Technical Education, Rio Salado College. This material is based upon work supported by the National Science Foundation under Grant #2500695. Any opinions, findings, and conclusions or recommendations expressed in this material are those of the author(s) and do not necessarily reflect the views of the National Science Foundation. This project is funded by the Advanced Technological Education program and is supported in part by funds from Intel Corporation under the ETSTE DCL.
B32: Contact: Rick Vaughn, Ph.D., Rick.Vaughn@riosalado.edu

Sheet 1 Roles
A1: Step 1 · Define the roles
A2: Start from the jobs employers hire for, not from programs. Build each profile from employer job descriptions, high-level certification domains, and industry advisory input.
A3: Legend: cream cells = your input · gray cells = calculated (don’t edit) · “Example” rows show the Arizona worked example; overwrite them.
A5: ID | B5: Role family (rename to fit your sector) | C5: O*NET code | D5: CIP code | E5: Example job titles | F5: Day one: what they do | G5: Year one | H5: Year three | I5: Employer job descriptions reviewed? | J5: Certification domains used? | K5: Advisory board reviewed? | L5: # Core competencies (from spine) | M5: Notes
A6: R1 | B6: Automation, Controls & Sensor Technologies | C6: 17-3023.00 | D6: 47.0105 | L6: =COUNTIF('2 Competency Spine'!H$6:H$300,"Core") -> 18
A7: R2 | B7: Data, Cybersecurity & Infrastructure | C7: 15-1231.00 | D7: 11.1003 | L7: =COUNTIF('2 Competency Spine'!I$6:I$300,"Core") -> 14
A8: R3 | B8: Equipment & Systems Maintenance | C8: 49-9071.00 | D8: 46.0401 | E8: Example: equipment technician | F8: Example: cleanroom gowning, lockout/tagout, run diagnostics software | G8: Example: service pneumatic and hydraulic systems; chamber seal leak detection | H8: Example: vacuum pump overhaul; plasma etch system repair | L8: =COUNTIF('2 Competency Spine'!J$6:J$300,"Core") -> 13 | M8: Example tasks drawn from this pathway’s crosswalk competencies; confirm with employers.
A9: R4 | B9: Manufacturing Operations | C9: 51-9141.00 | D9: 15.0616 | L9: =COUNTIF('2 Competency Spine'!K$6:K$300,"Core") -> 13
A10: R5 | B10: Process Engineering & Quality | C10: 17-2199.00 | D10: 14.3601 | L10: =COUNTIF('2 Competency Spine'!L$6:L$300,"Core") -> 15

Sheet 2 Competency Spine
A1: Step 2 · Map competencies to education
A2: One competency spine for every offering. Set the depth each role needs, then record where each competency is taught in each layer of the system.
A3: Legend: cream cells = your input · gray cells = calculated (don’t edit) · “Example” rows show the Arizona worked example; overwrite them.
A4: Competency | H4: Depth each role needs (Core / Working / Aware) | M4: Where it’s taught | S4: Check
A5: ID | B5: Tier | C5: Competency | D5: Skill category | E5: Pathway (role family) | F5: O*NET | G5: CIP | H5: ='1 Roles'!B6 -> Automation, Controls & Sensor Technologies | I5: ='1 Roles'!B7 -> Data, Cybersecurity & Infrastructure | J5: ='1 Roles'!B8 -> Equipment & Systems Maintenance | K5: ='1 Roles'!B9 -> Manufacturing Operations | L5: ='1 Roles'!B10 -> Process Engineering & Quality | M5: High school: ADE standards | N5: High school: PLTW | O5: Community college: MCCCD | P5: University: UA | Q5: Industry credential: Chip Path | R5: Non-credit / apprenticeship | S5: # layers teaching it | T5: Notes
A6: C-01 | B6: Core | C6: Communication | D6: Core employability | E6: All pathways | M6: 7.13; 1.7; 7.5; 7.2; 11.2; 1.8 | N6: PLTW Engineering (EDD, IED); PLTW Biomedical Science (BI); PLTW Gateway (DM) | O6: MNT140 | P6: CHEE 415 / SIE 465 | Q6: CP-101 | S6: =IF(OR(M6<>"",N6<>""),1,0)+IF(O6<>"",1,0)+IF(P6<>"",1,0)+IF(Q6<>"",1,0)+IF(R6<>"",1,0) -> 4
A7: C-02 | B7: Core | C7: Collaboration | D7: Core employability | E7: All pathways | M7: 2.8 | N7: PLTW Engineering (POE, CIM); PLTW Computer Science (SEC); PLTW Gateway (AR) | O7: MNT140 | P7: MSE/ECE 447/ SIE 483 | Q7: CP-102 | S7: =IF(OR(M7<>"",N7<>""),1,0)+IF(O7<>"",1,0)+IF(P7<>"",1,0)+IF(Q7<>"",1,0)+IF(R7<>"",1,0) -> 4
A8: C-03 | B8: Core | C8: Digital Fluency | D8: Core employability | E8: All pathways | M8: 7.12; 11.1 | N8: PLTW Engineering (IED, DE, CIM); PLTW Computer Science (CSE, CSA, SEC); PLTW Gateway (AC) | O8: AIT132 | P8: ECE 407/SIE 483/MSE 480 | Q8: CP-103 | S8: =IF(OR(M8<>"",N8<>""),1,0)+IF(O8<>"",1,0)+IF(P8<>"",1,0)+IF(Q8<>"",1,0)+IF(R8<>"",1,0) -> 4
A9: C-04 | B9: Core | C9: Critical Thinking & Problem Solving | D9: Core employability | E9: All pathways | M9: 7.1; 8.3; 5.12; 2.5; 9.5/9.6 | N9: PLTW Engineering (IED, POE, EDD); PLTW Biomedical Science (PBS, MI); PLTW Gateway (MD) | O9: AIT132 | P9: MSE/ECE 447/547 | Q9: CP-104 | S9: =IF(OR(M9<>"",N9<>""),1,0)+IF(O9<>"",1,0)+IF(P9<>"",1,0)+IF(Q9<>"",1,0)+IF(R9<>"",1,0) -> 4
A10: C-05 | B10: Core | C10: Numeracy | D10: Core employability | E10: All pathways | M10: 7.4 | N10: PLTW Engineering (POE, DE, IED); PLTW Biomedical Science (HBS, MI); PLTW Computer Science (CSA) | O10: MNT235 | P10: SIE 305/SIE 430 | Q10: CP-105 | S10: =IF(OR(M10<>"",N10<>""),1,0)+IF(O10<>"",1,0)+IF(P10<>"",1,0)+IF(Q10<>"",1,0)+IF(R10<>"",1,0) -> 4
A11: C-06 | B11: Core | C11: Reading & Writing | D11: Core employability | E11: All pathways | M11: 11.6/11.7; 2.8 | N11: PLTW Engineering (All, esp. EDD, IED); PLTW Biomedical Science (PBS, BI); PLTW Computer Science (SEC) | O11: ENG101 | P11: CHEE 415 | Q11: CP-106 | S11: =IF(OR(M11<>"",N11<>""),1,0)+IF(O11<>"",1,0)+IF(P11<>"",1,0)+IF(Q11<>"",1,0)+IF(R11<>"",1,0) -> 4
A12: K-01 | B12: Cluster | C12: Interpret basic electrical & circuit concepts & diagrams | D12: Technical Foundations | E12: All pathways | M12: 6.1-6.4; 7.2 | N12: PLTW Engineering (DE, POE) | O12: AIT132 | P12: ECE 220 | Q12: CP-101 / ELC-101 | S12: =IF(OR(M12<>"",N12<>""),1,0)+IF(O12<>"",1,0)+IF(P12<>"",1,0)+IF(Q12<>"",1,0)+IF(R12<>"",1,0) -> 4
A13: K-02 | B13: Cluster | C13: Use AI and ML tools to optimize manufacturing | D13: Data, Analysis, & Digital Tools | E13: All pathways | M13: 7.9 | N13: PLTW Computer Science (CSE, CSA) | O13: AIM230 | P13: SIE 574 | Q13: CP-103 / DAT-110 | S13: =IF(OR(M13<>"",N13<>""),1,0)+IF(O13<>"",1,0)+IF(P13<>"",1,0)+IF(Q13<>"",1,0)+IF(R13<>"",1,0) -> 4
A14: K-03 | B14: Cluster | C14: Use SPC charts and data tools to monitor processes | D14: Data, Analysis, & Digital Tools | E14: All pathways | M14: 7.1; 9.7 | N14: PLTW Engineering (IED, CIM) | O14: MNT108 | P14: SIE 540 | Q14: CP-103 / GTC-108 | S14: =IF(OR(M14<>"",N14<>""),1,0)+IF(O14<>"",1,0)+IF(P14<>"",1,0)+IF(Q14<>"",1,0)+IF(R14<>"",1,0) -> 4
A15: K-04 | B15: Cluster | C15: Recognize & respond to physical security & cybersecurity risks | D15: Safety, Security & Compliance | E15: All pathways | M15: Standard 11.0 | N15: PLTW Computer Science (SEC) | O15: CIS270 / ITS110 | P15: ECE 578 | Q15: CP-101 / CIS-110 | S15: =IF(OR(M15<>"",N15<>""),1,0)+IF(O15<>"",1,0)+IF(P15<>"",1,0)+IF(Q15<>"",1,0)+IF(R15<>"",1,0) -> 4
A16: K-05 | B16: Cluster | C16: Follow OSHA, COHE, & cleanroom safety protocols | D16: Safety, Security & Compliance | E16: All pathways | M16: 2.1; 2.8 | N16: PLTW Engineering (CIM, POE) | O16: MNT201 | P16: MSE / ECE / CHEE 515: | Q16: CP-101 / AIT-101 | S16: =IF(OR(M16<>"",N16<>""),1,0)+IF(O16<>"",1,0)+IF(P16<>"",1,0)+IF(Q16<>"",1,0)+IF(R16<>"",1,0) -> 4
A17: K-06 | B17: Cluster | C17: Diagnose issues in semiconductor tools & systems | D17: Equipment, Systems & Automation | E17: All pathways | M17: 5.12; 6.8-6.10 | N17: PLTW Engineering (POE, DE, CIM) | O17: AIT132 | P17: MSE / ECE 547L: | Q17: CP-104 / AIT-215 | S17: =IF(OR(M17<>"",N17<>""),1,0)+IF(O17<>"",1,0)+IF(P17<>"",1,0)+IF(Q17<>"",1,0)+IF(R17<>"",1,0) -> 4
... A22: K-11 | B22: Cluster | C22: Maintain cleanroom gowning & housekeeping | D22: Cross-Cutting | E22: All pathways | M22: 2.8 | N22: PLTW Biomedical Science (PBS, MI) | O22: MNT201 | P22: FASTLab Training: Cleanroom Operations & Protocols | Q22: CP-101 / AIT-101 | S22: =IF(OR(M22<>"",N22<>""),1,0)+IF(O22<>"",1,0)+IF(P22<>"",1,0)+IF(Q22<>"",1,0)+IF(R22<>"",1,0) -> 4
A23: AUT-01 | B23: Pathway | C23: Apply control systems concepts | E23: Automation, Controls & Sensor Technologies | F23: 17-3023.00 | G23: 47.0105 | H23: Core | M23: Standard 8.0; Standard 10.0 | O23: AIT215 | P23: ECE 441A / AME 455 | Q23: CP-102 / AIT-125 | S23: =IF(OR(M23<>"",N23<>""),1,0)+IF(O23<>"",1,0)+IF(P23<>"",1,0)+IF(Q23<>"",1,0)+IF(R23<>"",1,0) -> 4
A24: AUT-02 | B24: Pathway | C24: Interpret PLC & sensor logic | E24: Automation, Controls & Sensor Technologies | F24: 17-3023.00 | G24: 47.0105 | H24: Core | M24: 10.1-10.5; Standard 8.0 | O24: AIT210 | P24: CYBV 330 | Q24: CP-102 / AIT-125 | S24: =IF(OR(M24<>"",N24<>""),1,0)+IF(O24<>"",1,0)+IF(P24<>"",1,0)+IF(Q24<>"",1,0)+IF(R24<>"",1,0) -> 4
A25: AUT-03 | B25: Pathway | C25: Apply basic scripting for automation tasks | E25: Automation, Controls & Sensor Technologies | F25: 17-3023.00 | G25: 47.0105 | H25: Core | M25: 7.12 | O25: CIS156 | P25: ECE 101 / ECE 201 | Q25: CP-103 / DAT-110 | S25: =IF(OR(M25<>"",N25<>""),1,0)+IF(O25<>"",1,0)+IF(P25<>"",1,0)+IF(Q25<>"",1,0)+IF(R25<>"",1,0) -> 4
A26: AUT-04 | B26: Pathway | C26: Validate failsafe shutdown behaviors | E26: Automation, Controls & Sensor Technologies | F26: 17-3023.00 | G26: 47.0105 | H26: Core | M26: 2.6 | O26: AIT100 | P26: CYBV 330 / AME 463 | Q26: CP-101 / AIT-101 | S26: =IF(OR(M26<>"",N26<>""),1,0)+IF(O26<>"",1,0)+IF(P26<>"",1,0)+IF(Q26<>"",1,0)+IF(R26<>"",1,0) -> 4
A27: AUT-05 | B27: Pathway | C27: Implement machine safeguarding & interlocks | E27: Automation, Controls & Sensor Technologies | F27: 17-3023.00 | G27: 47.0105 | H27: Core | M27: 2.2; 2.5 | O27: AIT100 | P27: MNE 426 / CYBV 330 | Q27: CP-101 / AIT-101 | S27: =IF(OR(M27<>"",N27<>""),1,0)+IF(O27<>"",1,0)+IF(P27<>"",1,0)+IF(Q27<>"",1,0)+IF(R27<>"",1,0) -> 4
A28: AUT-06 | B28: Pathway | C28: Integrate robots | E28: Automation, Controls & Sensor Technologies | F28: 17-3023.00 | G28: 47.0105 | H28: Core | M28: 7.11 | O28: AIT270 | P28: AME 551 | Q28: CP-102 / AIT-220 | S28: =IF(OR(M28<>"",N28<>""),1,0)+IF(O28<>"",1,0)+IF(P28<>"",1,0)+IF(Q28<>"",1,0)+IF(R28<>"",1,0) -> 4
A29: AUT-07 | B29: Pathway | C29: Configure PLC I/O modules | E29: Automation, Controls & Sensor Technologies | F29: 17-3023.00 | G29: 47.0105 | H29: Core | M29: 10.2; 10.5 | O29: AIT210 | P29: CYBV 330 / ECE 372A | Q29: CP-102 / AIT-125 | S29: =IF(OR(M29<>"",N29<>""),1,0)+IF(O29<>"",1,0)+IF(P29<>"",1,0)+IF(Q29<>"",1,0)+IF(R29<>"",1,0) -> 4
A30: AUT-08 | B30: Pathway | C30: Validate sensor-based control performance | E30: Automation, Controls & Sensor Technologies | F30: 17-3023.00 | G30: 47.0105 | H30: Core | M30: 8.6-8.7 | O30: AIT215 | P30: ECE 442 | Q30: CP-102 / AIT-125 | S30: =IF(OR(M30<>"",N30<>""),1,0)+IF(O30<>"",1,0)+IF(P30<>"",1,0)+IF(Q30<>"",1,0)+IF(R30<>"",1,0) -> 4
A31: AUT-09 | B31: Pathway | C31: Control loop theory | D31: Technical Foundations | E31: Automation, Controls & Sensor Technologies | F31: 17-3023.00 | G31: 47.0105 | H31: Core | O31: ELC210 / MET220 | P31: ECE 441A | Q31: CP-102 / AIT-125 | S31: =IF(OR(M31<>"",N31<>""),1,0)+IF(O31<>"",1,0)+IF(P31<>"",1,0)+IF(Q31<>"",1,0)+IF(R31<>"",1,0) -> 3
A32: AUT-10 | B32: Pathway | C32: Sensor calibration principles | D32: Technical Foundations | E32: Automation, Controls & Sensor Technologies | F32: 17-3023.00 | G32: 47.0105 | H32: Core | O32: ELC210 / MET220 | P32: MSE / ECE 547L | Q32: CP-104 / MET-210 | S32: =IF(OR(M32<>"",N32<>""),1,0)+IF(O32<>"",1,0)+IF(P32<>"",1,0)+IF(Q32<>"",1,0)+IF(R32<>"",1,0) -> 3
A33: AUT-11 | B33: Pathway | C33: SCADA alarm analytics | D33: Data, Analysis, & Digital Tools | E33: Automation, Controls & Sensor Technologies | F33: 17-3023.00 | G33: 47.0105 | H33: Core | O33: ELC210 / MET220 | P33: CYBV 330 / SIE 506 | Q33: CP-103 / DAT-110 | S33: =IF(OR(M33<>"",N33<>""),1,0)+IF(O33<>"",1,0)+IF(P33<>"",1,0)+IF(Q33<>"",1,0)+IF(R33<>"",1,0) -> 3
A34: AUT-12 | B34: Pathway | C34: HMI telemetry visualization | D34: Data, Analysis, & Digital Tools | E34: Automation, Controls & Sensor Technologies | F34: 17-3023.00 | G34: 47.0105 | H34: Core | O34: ELC210 / MET220 | P34: CYBV 330 / ECE 372A | Q34: CP-102 / AIT-125 | S34: =IF(OR(M34<>"",N34<>""),1,0)+IF(O34<>"",1,0)+IF(P34<>"",1,0)+IF(Q34<>"",1,0)+IF(R34<>"",1,0) -> 3
A35: AUT-13 | B35: Pathway | C35: ISO 13849 safety circuit validation | D35: Safety, Security & Compliance | E35: Automation, Controls & Sensor Technologies | F35: 17-3023.00 | G35: 47.0105 | H35: Core | O35: MET220 / ELC210 | P35: SIE 508 / CYBV 330 | Q35: CP-101 / AIT-101 | S35: =IF(OR(M35<>"",N35<>""),1,0)+IF(O35<>"",1,0)+IF(P35<>"",1,0)+IF(Q35<>"",1,0)+IF(R35<>"",1,0) -> 3
A36: AUT-14 | B36: Pathway | C36: Fail-safe interlock testing | D36: Safety, Security & Compliance | E36: Automation, Controls & Sensor Technologies | F36: 17-3023.00 | G36: 47.0105 | H36: Core | O36: MET220 / ELC210 | P36: CYBV 330 / SIE 508 | Q36: CP-101 / AIT-101 | S36: =IF(OR(M36<>"",N36<>""),1,0)+IF(O36<>"",1,0)+IF(P36<>"",1,0)+IF(Q36<>"",1,0)+IF(R36<>"",1,0) -> 3
A37: AUT-15 | B37: Pathway | C37: SCADA system programming | D37: Equipment, Systems & Automation | E37: Automation, Controls & Sensor Technologies | F37: 17-3023.00 | G37: 47.0105 | H37: Core | O37: ELC210 / MET220 | P37: CYBV 330 | Q37: CP-102 / AIT-125 | S37: =IF(OR(M37<>"",N37<>""),1,0)+IF(O37<>"",1,0)+IF(P37<>"",1,0)+IF(Q37<>"",1,0)+IF(R37<>"",1,0) -> 3
A38: AUT-16 | B38: Pathway | C38: Programmable logic controller integration | D38: Equipment, Systems & Automation | E38: Automation, Controls & Sensor Technologies | F38: 17-3023.00 | G38: 47.0105 | H38: Core | O38: ELC210 | P38: CYBV 330 | Q38: CP-102 / AIT-125 | S38: =IF(OR(M38<>"",N38<>""),1,0)+IF(O38<>"",1,0)+IF(P38<>"",1,0)+IF(Q38<>"",1,0)+IF(R38<>"",1,0) -> 3
A39: AUT-17 | B39: Pathway | C39: PLC program modification | D39: Manufacturing Processes & Quality | E39: Automation, Controls & Sensor Technologies | F39: 17-3023.00 | G39: 47.0105 | H39: Core | O39: ELC210 | P39: CYBV 330 | Q39: CP-102 / AIT-125 | S39: =IF(OR(M39<>"",N39<>""),1,0)+IF(O39<>"",1,0)+IF(P39<>"",1,0)+IF(Q39<>"",1,0)+IF(R39<>"",1,0) -> 3
A40: AUT-18 | B40: Pathway | C40: Sensor error diagnostics | D40: Manufacturing Processes & Quality | E40: Automation, Controls & Sensor Technologies | F40: 17-3023.00 | G40: 47.0105 | H40: Core | O40: ELC210 / MET220 | P40: ECE 372A / SIE 508 | Q40: CP-104 / AIT-215 | S40: =IF(OR(M40<>"",N40<>""),1,0)+IF(O40<>"",1,0)+IF(P40<>"",1,0)+IF(Q40<>"",1,0)+IF(R40<>"",1,0) -> 3
A41: DAT-01 | B41: Pathway | C41: Apply AAA & CIA frameworks | E41: Data, Cybersecurity & Infrastructure | F41: 15-1231.00 | G41: 11.1003 | I41: Core | M41: 11.2; 11.3 | O41: ITS110 | P41: ECE 509 / CYBV 301 | Q41: CP-101 / CIS-110 | S41: =IF(OR(M41<>"",N41<>""),1,0)+IF(O41<>"",1,0)+IF(P41<>"",1,0)+IF(Q41<>"",1,0)+IF(R41<>"",1,0) -> 4
A42: DAT-02 | B42: Pathway | C42: Configure access controls on systems | E42: Data, Cybersecurity & Infrastructure | F42: 15-1231.00 | G42: 11.1003 | I42: Core | M42: 11.2 | O42: ITS120 | P42: ECE 524 / CYBV 326 | Q42: CP-101 / CIS-110 | S42: =IF(OR(M42<>"",N42<>""),1,0)+IF(O42<>"",1,0)+IF(P42<>"",1,0)+IF(Q42<>"",1,0)+IF(R42<>"",1,0) -> 4
A43: DAT-03 | B43: Pathway | C43: Support quality audits | E43: Data, Cybersecurity & Infrastructure | F43: 15-1231.00 | G43: 11.1003 | I43: Core | M43: 9.8 | O43: MNT235 | P43: SIE 567 / SIE 530 | Q43: CP-103 / MET-210 | S43: =IF(OR(M43<>"",N43<>""),1,0)+IF(O43<>"",1,0)+IF(P43<>"",1,0)+IF(Q43<>"",1,0)+IF(R43<>"",1,0) -> 4
A44: DAT-04 | B44: Pathway | C44: Monitor data integrity | E44: Data, Cybersecurity & Infrastructure | F44: 15-1231.00 | G44: 11.1003 | I44: Core | M44: 11.3 | O44: MNT108 | P44: SFWE 501 / ECE 519 | Q44: CP-103 / DAT-110 | S44: =IF(OR(M44<>"",N44<>""),1,0)+IF(O44<>"",1,0)+IF(P44<>"",1,0)+IF(Q44<>"",1,0)+IF(R44<>"",1,0) -> 4
A45: DAT-05 | B45: Pathway | C45: Database design principles | D45: Technical Foundations | E45: Data, Cybersecurity & Infrastructure | F45: 15-1231.00 | G45: 11.1003 | I45: Core | O45: CIS105 / BPC110 | P45: MIS 502 / MIS 531 | Q45: CP-103 / DAT-110 | S45: =IF(OR(M45<>"",N45<>""),1,0)+IF(O45<>"",1,0)+IF(P45<>"",1,0)+IF(Q45<>"",1,0)+IF(R45<>"",1,0) -> 3
A46: DAT-06 | B46: Pathway | C46: OT cybersecurity threat hunting | D46: Data, Analysis, & Digital Tools | E46: Data, Cybersecurity & Infrastructure | F46: 15-1231.00 | G46: 11.1003 | I46: Core | O46: CIS114DE / ITS110 | P46: ECE 571 / CYBV 435 | Q46: CP-101 / CIS-190 | S46: =IF(OR(M46<>"",N46<>""),1,0)+IF(O46<>"",1,0)+IF(P46<>"",1,0)+IF(Q46<>"",1,0)+IF(R46<>"",1,0) -> 3
A47: DAT-07 | B47: Pathway | C47: Fab database SQL querying | D47: Data, Analysis, & Digital Tools | E47: Data, Cybersecurity & Infrastructure | F47: 15-1231.00 | G47: 11.1003 | I47: Core | O47: CIS105 / BPC110 | P47: MIS 502 / ISTA 322 | Q47: CP-103 / DAT-110 | S47: =IF(OR(M47<>"",N47<>""),1,0)+IF(O47<>"",1,0)+IF(P47<>"",1,0)+IF(Q47<>"",1,0)+IF(R47<>"",1,0) -> 3
A48: DAT-08 | B48: Pathway | C48: Fab cyber threat monitoring | D48: Safety, Security & Compliance | E48: Data, Cybersecurity & Infrastructure | F48: 15-1231.00 | G48: 11.1003 | I48: Core | O48: CIS114DE / ITS110 | P48: ECE 519 / SFWE 502 | Q48: CP-101 / CIS-190 | S48: =IF(OR(M48<>"",N48<>""),1,0)+IF(O48<>"",1,0)+IF(P48<>"",1,0)+IF(Q48<>"",1,0)+IF(R48<>"",1,0) -> 3
A49: DAT-09 | B49: Pathway | C49: Securing legacy equipment endpoints | D49: Safety, Security & Compliance | E49: Data, Cybersecurity & Infrastructure | F49: 15-1231.00 | G49: 11.1003 | I49: Core | O49: CIS114DE / ITS110 | P49: ECE 576B / CYBV 470 | Q49: CP-101 / CIS-190 | S49: =IF(OR(M49<>"",N49<>""),1,0)+IF(O49<>"",1,0)+IF(P49<>"",1,0)+IF(Q49<>"",1,0)+IF(R49<>"",1,0) -> 3
A50: DAT-10 | B50: Pathway | C50: Edge computing deployment | D50: Equipment, Systems & Automation | E50: Data, Cybersecurity & Infrastructure | F50: 15-1231.00 | G50: 11.1003 | I50: Core | O50: CIS114DE / ITS110 | P50: ECE 513 / ECE 569 | Q50: CP-103 / DAT-110 | S50: =IF(OR(M50<>"",N50<>""),1,0)+IF(O50<>"",1,0)+IF(P50<>"",1,0)+IF(Q50<>"",1,0)+IF(R50<>"",1,0) -> 3
A51: DAT-11 | B51: Pathway | C51: MES server integration | D51: Equipment, Systems & Automation | E51: Data, Cybersecurity & Infrastructure | F51: 15-1231.00 | G51: 11.1003 | I51: Core | O51: CIS105 / BPC110 | P51: SIE 554A / ECE 573 | Q51: CP-102 / AIT-125 | S51: =IF(OR(M51<>"",N51<>""),1,0)+IF(O51<>"",1,0)+IF(P51<>"",1,0)+IF(Q51<>"",1,0)+IF(R51<>"",1,0) -> 3
A52: DAT-12 | B52: Pathway | C52: Data pipeline monitoring | D52: Manufacturing Processes & Quality | E52: Data, Cybersecurity & Infrastructure | F52: 15-1231.00 | G52: 11.1003 | I52: Core | O52: CIS122 / BPC110 | P52: ECE 523 / MIS 545 | Q52: CP-103 / DAT-110 | S52: =IF(OR(M52<>"",N52<>""),1,0)+IF(O52<>"",1,0)+IF(P52<>"",1,0)+IF(Q52<>"",1,0)+IF(R52<>"",1,0) -> 3
A53: DAT-13 | B53: Pathway | C53: Process telemetry analysis | D53: Manufacturing Processes & Quality | E53: Data, Cybersecurity & Infrastructure | F53: 15-1231.00 | G53: 11.1003 | I53: Core | O53: DAT110 / MET210 | P53: ECE 546 / ECE 517 | Q53: CP-103 / DAT-110 | S53: =IF(OR(M53<>"",N53<>""),1,0)+IF(O53<>"",1,0)+IF(P53<>"",1,0)+IF(Q53<>"",1,0)+IF(R53<>"",1,0) -> 3
A54: DAT-14 | B54: Pathway | C54: OT network topology | D54: Technical Foundations | E54: Data, Cybersecurity & Infrastructure | F54: 15-1231.00 | G54: 11.1003 | I54: Core | O54: CIS114DE / ITS110 | P54: ECE 578 / ECE 512 | Q54: CP-101 / CIS-190 | S54: =IF(OR(M54<>"",N54<>""),1,0)+IF(O54<>"",1,0)+IF(P54<>"",1,0)+IF(Q54<>"",1,0)+IF(R54<>"",1,0) -> 3
A55: EQP-01 | B55: Pathway | C55: Use diagnostics software | E55: Equipment & Systems Maintenance | F55: 49-9071.00 | G55: 46.0401 | J55: Core | M55: 7.12 | O55: AIT210 | P55: ECE 446 / MSE 446 | Q55: CP-104 / AIT-215 | S55: =IF(OR(M55<>"",N55<>""),1,0)+IF(O55<>"",1,0)+IF(P55<>"",1,0)+IF(Q55<>"",1,0)+IF(R55<>"",1,0) -> 4
A56: EQP-02 | B56: Pathway | C56: Apply LOTO on equipment | E56: Equipment & Systems Maintenance | F56: 49-9071.00 | G56: 46.0401 | J56: Core | M56: 2.1 | O56: AIT100 | P56: MSE 447L / ECE 547L | Q56: CP-101 / AIT-101 | S56: =IF(OR(M56<>"",N56<>""),1,0)+IF(O56<>"",1,0)+IF(P56<>"",1,0)+IF(Q56<>"",1,0)+IF(R56<>"",1,0) -> 4
A57: EQP-03 | B57: Pathway | C57: Service pneumatic & hydraulic systems | E57: Equipment & Systems Maintenance | F57: 49-9071.00 | G57: 46.0401 | J57: Core | M57: Standard 5.0 | O57: AIT115 / AIT120 | P57: AME 455 | Q57: CP-102 / AIT-120 | S57: =IF(OR(M57<>"",N57<>""),1,0)+IF(O57<>"",1,0)+IF(P57<>"",1,0)+IF(Q57<>"",1,0)+IF(R57<>"",1,0) -> 4
A58: EQP-04 | B58: Pathway | C58: Mechanical drive troubleshooting | D58: Technical Foundations | E58: Equipment & Systems Maintenance | F58: 49-9071.00 | G58: 46.0401 | J58: Core | O58: MET150 / MET215 | P58: AME 352 | Q58: CP-102 / AIT-120 | S58: =IF(OR(M58<>"",N58<>""),1,0)+IF(O58<>"",1,0)+IF(P58<>"",1,0)+IF(Q58<>"",1,0)+IF(R58<>"",1,0) -> 3
A59: EQP-05 | B59: Pathway | C59: Vacuum pressure physics | D59: Technical Foundations | E59: Equipment & Systems Maintenance | F59: 49-9071.00 | G59: 46.0401 | J59: Core | O59: SEM101 / MET215 | P59: MSE 437 / CHEE 437 | Q59: CP-104 / SMI-101 | S59: =IF(OR(M59<>"",N59<>""),1,0)+IF(O59<>"",1,0)+IF(P59<>"",1,0)+IF(Q59<>"",1,0)+IF(R59<>"",1,0) -> 3
A60: EQP-06 | B60: Pathway | C60: Sensor diagnostic log interpretation | D60: Data, Analysis, & Digital Tools | E60: Equipment & Systems Maintenance | F60: 49-9071.00 | G60: 46.0401 | J60: Core | O60: MET215 / ELE211 | P60: ECE 415 / CHEE 415 | Q60: CP-104 / AIT-215 | S60: =IF(OR(M60<>"",N60<>""),1,0)+IF(O60<>"",1,0)+IF(P60<>"",1,0)+IF(Q60<>"",1,0)+IF(R60<>"",1,0) -> 3
A61: EQP-07 | B61: Pathway | C61: Predictive maintenance software | D61: Data, Analysis, & Digital Tools | E61: Equipment & Systems Maintenance | F61: 49-9071.00 | G61: 46.0401 | J61: Core | O61: MET215 / MET210 | P61: SIE 431 / ECE 431 | Q61: CP-103 / DAT-110 | S61: =IF(OR(M61<>"",N61<>""),1,0)+IF(O61<>"",1,0)+IF(P61<>"",1,0)+IF(Q61<>"",1,0)+IF(R61<>"",1,0) -> 3
A62: EQP-08 | B62: Pathway | C62: Chemical delivery system safety | D62: Safety, Security & Compliance | E62: Equipment & Systems Maintenance | F62: 49-9071.00 | G62: 46.0401 | J62: Core | O62: SEM101 / MET101 | P62: CHEE 515 / MSE 515 | Q62: CP-101 / EHS-105 | S62: =IF(OR(M62<>"",N62<>""),1,0)+IF(O62<>"",1,0)+IF(P62<>"",1,0)+IF(Q62<>"",1,0)+IF(R62<>"",1,0) -> 3
A63: EQP-09 | B63: Pathway | C63: High-voltage isolation protocol | D63: Safety, Security & Compliance | E63: Equipment & Systems Maintenance | F63: 49-9071.00 | G63: 46.0401 | J63: Core | O63: ELC115 / MET101 | P63: ECE 351C | Q63: CP-101 / ELC-101 | S63: =IF(OR(M63<>"",N63<>""),1,0)+IF(O63<>"",1,0)+IF(P63<>"",1,0)+IF(Q63<>"",1,0)+IF(R63<>"",1,0) -> 3
A64: EQP-10 | B64: Pathway | C64: Plasma etch system repair | D64: Equipment, Systems & Automation | E64: Equipment & Systems Maintenance | F64: 49-9071.00 | G64: 46.0401 | J64: Core | O64: SEM201 / MET215 | P64: MSE 447L / ECE 447L | Q64: CP-104 / AIT-215 | S64: =IF(OR(M64<>"",N64<>""),1,0)+IF(O64<>"",1,0)+IF(P64<>"",1,0)+IF(Q64<>"",1,0)+IF(R64<>"",1,0) -> 3
A65: EQP-11 | B65: Pathway | C65: Robotic arm calibration | D65: Equipment, Systems & Automation | E65: Equipment & Systems Maintenance | F65: 49-9071.00 | G65: 46.0401 | J65: Core | O65: MET180 / MET220 | P65: AME 463 / ECE 463 | Q65: CP-102 / AIT-220 | S65: =IF(OR(M65<>"",N65<>""),1,0)+IF(O65<>"",1,0)+IF(P65<>"",1,0)+IF(Q65<>"",1,0)+IF(R65<>"",1,0) -> 3
A66: EQP-12 | B66: Pathway | C66: Vacuum pump overhaul | D66: Manufacturing Processes & Quality | E66: Equipment & Systems Maintenance | F66: 49-9071.00 | G66: 46.0401 | J66: Core | O66: MET215 | P66: MSE 447L / ECE 547L | Q66: CP-104 / AIT-215 | S66: =IF(OR(M66<>"",N66<>""),1,0)+IF(O66<>"",1,0)+IF(P66<>"",1,0)+IF(Q66<>"",1,0)+IF(R66<>"",1,0) -> 3
A67: EQP-13 | B67: Pathway | C67: Chamber seal leak detection | D67: Manufacturing Processes & Quality | E67: Equipment & Systems Maintenance | F67: 49-9071.00 | G67: 46.0401 | J67: Core | O67: MET215 / SEM201 | P67: MSE 447L / ECE 447L | Q67: CP-104 / AIT-215 | S67: =IF(OR(M67<>"",N67<>""),1,0)+IF(O67<>"",1,0)+IF(P67<>"",1,0)+IF(Q67<>"",1,0)+IF(R67<>"",1,0) -> 3
A68: MFG-01 | B68: Pathway | C68: Use basic materials science concepts | E68: Manufacturing Operations | F68: 51-9141.00 | G68: 15.0616 | K68: Core | M68: 1.7; 3.1 | O68: MNT225 | P68: MSE 240 / MSE 331R | Q68: CP-101 / SMI-101 | S68: =IF(OR(M68<>"",N68<>""),1,0)+IF(O68<>"",1,0)+IF(P68<>"",1,0)+IF(Q68<>"",1,0)+IF(R68<>"",1,0) -> 4
A69: MFG-02 | B69: Pathway | C69: Follow wafer flow steps | E69: Manufacturing Operations | F69: 51-9141.00 | G69: 15.0616 | K69: Core | M69: 4.4 | O69: MNT116 | P69: ECE / MSE 546 | Q69: CP-101 / SMI-101 | S69: =IF(OR(M69<>"",N69<>""),1,0)+IF(O69<>"",1,0)+IF(P69<>"",1,0)+IF(Q69<>"",1,0)+IF(R69<>"",1,0) -> 4
A70: MFG-03 | B70: Pathway | C70: Semiconductor Manufacturing | D70: Semiconductor Manufacturing | E70: Manufacturing Operations | F70: 51-9141.00 | G70: 15.0616 | K70: Core | O70: MNT115 | P70: ECE / MSE 546 | Q70: CP-101 / SMI-101 | S70: =IF(OR(M70<>"",N70<>""),1,0)+IF(O70<>"",1,0)+IF(P70<>"",1,0)+IF(Q70<>"",1,0)+IF(R70<>"",1,0) -> 3
A71: MFG-04 | B71: Pathway | C71: Wafer inspection techniques | D71: Technical Foundations | E71: Manufacturing Operations | F71: 51-9141.00 | G71: 15.0616 | K71: Core | O71: SEM101 / SEM110 | P71: MSE / ECE 580 | Q71: CP-104 / MET-210 | S71: =IF(OR(M71<>"",N71<>""),1,0)+IF(O71<>"",1,0)+IF(P71<>"",1,0)+IF(Q71<>"",1,0)+IF(R71<>"",1,0) -> 3
A72: MFG-05 | B72: Pathway | C72: Cleanroom protocol adherence | D72: Technical Foundations | E72: Manufacturing Operations | F72: 51-9141.00 | G72: 15.0616 | K72: Core | O72: SEM101 | P72: MSE / ECE 547 (FASTLab Protocol) | Q72: CP-101 / AIT-101 | S72: =IF(OR(M72<>"",N72<>""),1,0)+IF(O72<>"",1,0)+IF(P72<>"",1,0)+IF(Q72<>"",1,0)+IF(R72<>"",1,0) -> 3
A73: MFG-06 | B73: Pathway | C73: Manufacturing execution system logging | D73: Data, Analysis, & Digital Tools | E73: Manufacturing Operations | F73: 51-9141.00 | G73: 15.0616 | K73: Core | O73: SEM101 / BPC110 | P73: SIE 462 / SIE 562 | Q73: CP-103 / DAT-110 | S73: =IF(OR(M73<>"",N73<>""),1,0)+IF(O73<>"",1,0)+IF(P73<>"",1,0)+IF(Q73<>"",1,0)+IF(R73<>"",1,0) -> 3
A74: MFG-07 | B74: Pathway | C74: Equipment run log parsing | D74: Data, Analysis, & Digital Tools | E74: Manufacturing Operations | F74: 51-9141.00 | G74: 15.0616 | K74: Core | O74: CIS122 / BPC110 | P74: ECE 479 / SIE 410A | Q74: CP-103 / DAT-110 | S74: =IF(OR(M74<>"",N74<>""),1,0)+IF(O74<>"",1,0)+IF(P74<>"",1,0)+IF(Q74<>"",1,0)+IF(R74<>"",1,0) -> 3
A75: MFG-08 | B75: Pathway | C75: Pyrophoric gas safety | D75: Safety, Security & Compliance | E75: Manufacturing Operations | F75: 51-9141.00 | G75: 15.0616 | K75: Core | O75: SEM101 / MET101 | P75: CHE / MSE 412 (or EHS Safety Modules) | Q75: CP-101 / EHS-105 | S75: =IF(OR(M75<>"",N75<>""),1,0)+IF(O75<>"",1,0)+IF(P75<>"",1,0)+IF(Q75<>"",1,0)+IF(R75<>"",1,0) -> 3
A76: MFG-09 | B76: Pathway | C76: Lockout/tagout execution | D76: Safety, Security & Compliance | E76: Manufacturing Operations | F76: 51-9141.00 | G76: 15.0616 | K76: Core | O76: SEM101 / MET101 | P76: ENGR 495A / EHS Tool Safety | Q76: CP-101 / AIT-101 | S76: =IF(OR(M76<>"",N76<>""),1,0)+IF(O76<>"",1,0)+IF(P76<>"",1,0)+IF(Q76<>"",1,0)+IF(R76<>"",1,0) -> 3
A77: MFG-10 | B77: Pathway | C77: Automated material handling system operation | D77: Equipment, Systems & Automation | E77: Manufacturing Operations | F77: 51-9141.00 | G77: 15.0616 | K77: Core | O77: MET180 / MET220 | P77: SIE 482 / SIE 582 | Q77: CP-102 / AIT-220 | S77: =IF(OR(M77<>"",N77<>""),1,0)+IF(O77<>"",1,0)+IF(P77<>"",1,0)+IF(Q77<>"",1,0)+IF(R77<>"",1,0) -> 3
A78: MFG-11 | B78: Pathway | C78: FOUP loading and unloading | D78: Equipment, Systems & Automation | E78: Manufacturing Operations | F78: 51-9141.00 | G78: 15.0616 | K78: Core | O78: SEM101 / MET180 | P78: MSE / ECE 547 | Q78: CP-102 / SMI-101 | S78: =IF(OR(M78<>"",N78<>""),1,0)+IF(O78<>"",1,0)+IF(P78<>"",1,0)+IF(Q78<>"",1,0)+IF(R78<>"",1,0) -> 3
A79: MFG-12 | B79: Pathway | C79: Photolithography execution | D79: Manufacturing Processes & Quality | E79: Manufacturing Operations | F79: 51-9141.00 | G79: 15.0616 | K79: Core | O79: SEM110 | P79: ECE / MSE 546 (Lab: MSE 547) | Q79: CP-101 / SMI-101 | S79: =IF(OR(M79<>"",N79<>""),1,0)+IF(O79<>"",1,0)+IF(P79<>"",1,0)+IF(Q79<>"",1,0)+IF(R79<>"",1,0) -> 3
A80: MFG-13 | B80: Pathway | C80: Chemical mechanical planarization | D80: Manufacturing Processes & Quality | E80: Manufacturing Operations | F80: 51-9141.00 | G80: 15.0616 | K80: Core | O80: SEM110 / SEM210 | P80: ECE / MSE 546 | Q80: CP-101 / SMI-101 | S80: =IF(OR(M80<>"",N80<>""),1,0)+IF(O80<>"",1,0)+IF(P80<>"",1,0)+IF(Q80<>"",1,0)+IF(R80<>"",1,0) -> 3
A81: PEQ-01 | B81: Pathway | C81: Apply semiconductor device physics | E81: Process Engineering & Quality | F81: 17-2199.00 | G81: 14.3601 | L81: Core | M81: 4.1-4.7; 6.3 | O81: MNT225 | P81: PHYS 561 / ECE 554 | Q81: CP-101 / SMI-101 | S81: =IF(OR(M81<>"",N81<>""),1,0)+IF(O81<>"",1,0)+IF(P81<>"",1,0)+IF(Q81<>"",1,0)+IF(R81<>"",1,0) -> 4
A82: PEQ-02 | B82: Pathway | C82: Use EDA & yield analysis tools | E82: Process Engineering & Quality | F82: 17-2199.00 | G82: 14.3601 | L82: Core | M82: 7.8; 3.4 | O82: MNT215 | P82: ECE 503C / ECE 506 | Q82: CP-103 / DAT-110 | S82: =IF(OR(M82<>"",N82<>""),1,0)+IF(O82<>"",1,0)+IF(P82<>"",1,0)+IF(Q82<>"",1,0)+IF(R82<>"",1,0) -> 4
A83: PEQ-03 | B83: Pathway | C83: Perform SP analyses | E83: Process Engineering & Quality | F83: 17-2199.00 | G83: 14.3601 | L83: Core | M83: 9.7 | O83: MNT108 | P83: SIE 530 / SIE 506 | Q83: CP-103 / GTC-108 | S83: =IF(OR(M83<>"",N83<>""),1,0)+IF(O83<>"",1,0)+IF(P83<>"",1,0)+IF(Q83<>"",1,0)+IF(R83<>"",1,0) -> 4
A84: PEQ-04 | B84: Pathway | C84: Implement process improvement actions | E84: Process Engineering & Quality | F84: 17-2199.00 | G84: 14.3601 | L84: Core | M84: Standard 9.0 | O84: AIT132 | P84: SIE 506 | Q84: CP-103 / MET-210 | S84: =IF(OR(M84<>"",N84<>""),1,0)+IF(O84<>"",1,0)+IF(P84<>"",1,0)+IF(Q84<>"",1,0)+IF(R84<>"",1,0) -> 4
A85: PEQ-05 | B85: Pathway | C85: Analyze manufacturing yield data | E85: Process Engineering & Quality | F85: 17-2199.00 | G85: 14.3601 | L85: Core | M85: 3.4; 7.4 | O85: MNT235 | P85: SIE 530 / MSE 546 | Q85: CP-103 / DAT-110 | S85: =IF(OR(M85<>"",N85<>""),1,0)+IF(O85<>"",1,0)+IF(P85<>"",1,0)+IF(Q85<>"",1,0)+IF(R85<>"",1,0) -> 4
A86: PEQ-06 | B86: Pathway | C86: Material science application | D86: Technical Foundations | E86: Process Engineering & Quality | F86: 17-2199.00 | G86: 14.3601 | L86: Core | O86: MET111 / SEM101 | P86: MSE 580 / PHYS 560A | Q86: CP-101 / SMI-101 | S86: =IF(OR(M86<>"",N86<>""),1,0)+IF(O86<>"",1,0)+IF(P86<>"",1,0)+IF(Q86<>"",1,0)+IF(R86<>"",1,0) -> 3
A87: PEQ-07 | B87: Pathway | C87: Yield loss mechanics | D87: Technical Foundations | E87: Process Engineering & Quality | F87: 17-2199.00 | G87: 14.3601 | L87: Core | O87: SEM110 / SEM210 | P87: MSE / ECE 546 | Q87: CP-104 / SMI-101 | S87: =IF(OR(M87<>"",N87<>""),1,0)+IF(O87<>"",1,0)+IF(P87<>"",1,0)+IF(Q87<>"",1,0)+IF(R87<>"",1,0) -> 3
A88: PEQ-08 | B88: Pathway | C88: Python for yield modeling | D88: Data, Analysis, & Digital Tools | E88: Process Engineering & Quality | F88: 17-2199.00 | G88: 14.3601 | L88: Core | O88: CIS122 / DAT110 | P88: ECE 503C / DATA 510 | Q88: CP-103 / DAT-110 | S88: =IF(OR(M88<>"",N88<>""),1,0)+IF(O88<>"",1,0)+IF(P88<>"",1,0)+IF(Q88<>"",1,0)+IF(R88<>"",1,0) -> 3
A89: PEQ-09 | B89: Pathway | C89: Multivariate process data analysis | D89: Data, Analysis, & Digital Tools | E89: Process Engineering & Quality | F89: 17-2199.00 | G89: 14.3601 | L89: Core | O89: DAT110 / MET210 | P89: STAT / MATH 571B | Q89: CP-103 / DAT-110 | S89: =IF(OR(M89<>"",N89<>""),1,0)+IF(O89<>"",1,0)+IF(P89<>"",1,0)+IF(Q89<>"",1,0)+IF(R89<>"",1,0) -> 3
A90: PEQ-10 | B90: Pathway | C90: EPA chemical waste compliance | D90: Safety, Security & Compliance | E90: Process Engineering & Quality | F90: 17-2199.00 | G90: 14.3601 | L90: Core | O90: SEM101 / MET101 | P90: CHEE / MSE 515 | Q90: CP-101 / EHS-105 | S90: =IF(OR(M90<>"",N90<>""),1,0)+IF(O90<>"",1,0)+IF(P90<>"",1,0)+IF(Q90<>"",1,0)+IF(R90<>"",1,0) -> 3
A91: PEQ-11 | B91: Pathway | C91: Process safety management | D91: Safety, Security & Compliance | E91: Process Engineering & Quality | F91: 17-2199.00 | G91: 14.3601 | L91: Core | O91: MET101 / GTC108 | P91: CHEE / MSE 515 | Q91: CP-101 / EHS-105 | S91: =IF(OR(M91<>"",N91<>""),1,0)+IF(O91<>"",1,0)+IF(P91<>"",1,0)+IF(Q91<>"",1,0)+IF(R91<>"",1,0) -> 3
A92: PEQ-12 | B92: Pathway | C92: Thermal deposition tuning | D92: Equipment, Systems & Automation | E92: Process Engineering & Quality | F92: 17-2199.00 | G92: 14.3601 | L92: Core | O92: SEM110 / SEM210 | P92: MSE / ECE 547L | Q92: CP-104 / SMI-101 | S92: =IF(OR(M92<>"",N92<>""),1,0)+IF(O92<>"",1,0)+IF(P92<>"",1,0)+IF(Q92<>"",1,0)+IF(R92<>"",1,0) -> 3
A93: PEQ-13 | B93: Pathway | C93: Epitaxy tool characterization | D93: Equipment, Systems & Automation | E93: Process Engineering & Quality | F93: 17-2199.00 | G93: 14.3601 | L93: Core | O93: SEM210 | P93: MSE 580 / MSE 547L | Q93: CP-104 / SMI-101 | S93: =IF(OR(M93<>"",N93<>""),1,0)+IF(O93<>"",1,0)+IF(P93<>"",1,0)+IF(Q93<>"",1,0)+IF(R93<>"",1,0) -> 3
A94: PEQ-14 | B94: Pathway | C94: Defect root cause analysis | D94: Manufacturing Processes & Quality | E94: Process Engineering & Quality | F94: 17-2199.00 | G94: 14.3601 | L94: Core | O94: GTC108 / MET210 | P94: MSE 580 | Q94: CP-104 / MET-210 | S94: =IF(OR(M94<>"",N94<>""),1,0)+IF(O94<>"",1,0)+IF(P94<>"",1,0)+IF(Q94<>"",1,0)+IF(R94<>"",1,0) -> 3
A95: PEQ-15 | B95: Pathway | C95: Design of experiments | D95: Manufacturing Processes & Quality | E95: Process Engineering & Quality | F95: 17-2199.00 | G95: 14.3601 | L95: Core | O95: GTC108 / SEM210 | P95: MATH 571B / SIE 530 | Q95: CP-103 / GTC-108 | S95: =IF(OR(M95<>"",N95<>""),1,0)+IF(O95<>"",1,0)+IF(P95<>"",1,0)+IF(Q95<>"",1,0)+IF(R95<>"",1,0) -> 3
A97: Starter defaults: each pathway competency is marked Core for its own role family; all other depth cells are blank for you to set with employers. Add rows below row 95 for new competencies (copy a row to keep the formulas).

Sheet 3 Partner Roles
A1: Step 3 · Assign partner roles
A2: Give every partner a clear lane: one Lead (L) per function, everyone else Supports (S). Rename the partner columns to fit your region.
A3: Legend: cream cells = your input · gray cells = calculated (don’t edit) · “Example” rows show the Arizona worked example; overwrite them.
A5: Function | B5: Description | C5: High schools | D5: Community colleges | E5: Universities | F5: Employers | G5: Certification bodies | H5: State & regional | I5: [Add partner] | J5: # leads | K5: Status
A6: Organizations in your region | B6: Who fills each column | C6: Example: Chandler Unified School District | D6: Example: Rio Salado College, Maricopa district | E6: Example: NAU, ASU, University of Arizona | F6: Example: TSMC and advisory employers | G6: Example: SEMI Foundation, NOCTI | H6: Example: Arizona Commerce Authority
A7: Career exposure | B7: Tours, industry speakers, career awareness for students, parents, counselors | C7: L | D7: S | E7: S | F7: S | H7: S | J7: =COUNTIF(C7:I7,"L") -> 1 | K7: =IF(A7="","",IF(J7=0,"No lead",IF(J7>1,"Multiple leads: clarify","OK"))) -> OK
A8: Dual enrollment | B8: College credit in high school, using the same industry-endorsed certificate | C8: L | D8: L | J8: =COUNTIF(C8:I8,"L") -> 2 | K8: =IF(A8="","",IF(J8=0,"No lead",IF(J8>1,"Multiple leads: clarify","OK"))) -> Multiple leads: clarify
A9: Stackable credentials | B9: Certificates that stack into a degree, each with job value | D9: L | F9: S | G9: S | J9: =COUNTIF(C9:I9,"L") -> 1 | K9: =IF(A9="","",IF(J9=0,"No lead",IF(J9>1,"Multiple leads: clarify","OK"))) -> OK
A10: Core technician training | B10: Credit and non-credit technical instruction | D10: L | F10: S | J10: =COUNTIF(C10:I10,"L") -> 1 | K10: =IF(A10="","",IF(J10=0,"No lead",IF(J10>1,"Multiple leads: clarify","OK"))) -> OK
A11: Hands-on lab access | B11: Cleanroom and tool time beyond college labs | D11: S | E11: L | F11: S | J11: =COUNTIF(C11:I11,"L") -> 1 | K11: =IF(A11="","",IF(J11=0,"No lead",IF(J11>1,"Multiple leads: clarify","OK"))) -> OK
A12: Articulation and transfer | B12: Credit transfer to bachelor’s completion | D12: S | E12: L | J12: =COUNTIF(C12:I12,"L") -> 1 | K12: =IF(A12="","",IF(J12=0,"No lead",IF(J12>1,"Multiple leads: clarify","OK"))) -> OK
A13: Job descriptions and advisory input | B13: Defines roles and competencies; reviews the map | D13: S | F13: L | J13: =COUNTIF(C13:I13,"L") -> 1 | K13: =IF(A13="","",IF(J13=0,"No lead",IF(J13>1,"Multiple leads: clarify","OK"))) -> OK
A14: Apprenticeships | B14: On-the-job learning with related technical instruction | D14: S | F14: L | G14: S | J14: =COUNTIF(C14:I14,"L") -> 1 | K14: =IF(A14="","",IF(J14=0,"No lead",IF(J14>1,"Multiple leads: clarify","OK"))) -> OK
A15: Industry certification | B15: Third-party validation of competencies | D15: S | F15: S | G15: L | J15: =COUNTIF(C15:I15,"L") -> 1 | K15: =IF(A15="","",IF(J15=0,"No lead",IF(J15>1,"Multiple leads: clarify","OK"))) -> OK
A16: Investment and convening | B16: Statewide funding, coordination, regional planning | D16: S | F16: S | H16: L | J16: =COUNTIF(C16:I16,"L") -> 1 | K16: =IF(A16="","",IF(J16=0,"No lead",IF(J16>1,"Multiple leads: clarify","OK"))) -> OK
J17: =COUNTIF(C17:I17,"L") -> 0 | K17: =IF(A17="","",IF(J17=0,"No lead",IF(J17>1,"Multiple leads: clarify","OK")))
J18: =COUNTIF(C18:I18,"L") -> 0 | K18: =IF(A18="","",IF(J18=0,"No lead",IF(J18>1,"Multiple leads: clarify","OK")))
J19: =COUNTIF(C19:I19,"L") -> 0 | K19: =IF(A19="","",IF(J19=0,"No lead",IF(J19>1,"Multiple leads: clarify","OK")))
A21: Example marks show the Arizona worked example. Dual enrollment intentionally has two leads (high school and college) to show the flag; decide whether shared leadership works for you.

Sheet 4 Overlap and Gaps
A1: Step 4 · Find overlaps and gaps
A2: Calculated from the spine. Gaps need an owner. For each “Check” row, answer the three questions: three Yes answers mean duplication to coordinate; otherwise it may be a healthy on-ramp.
A3: Legend: cream cells = your input · gray cells = calculated (don’t edit) · “Example” rows show the Arizona worked example; overwrite them.
A5: ID | B5: Competency | C5: Tier | D5: Pathway | E5: Community college offering(s) | F5: # CC courses | G5: High school on-ramp? | H5: # layers teaching it | I5: Status | J5: Same audience? | K5: Same depth? | L5: Same credential? | M5: Verdict | N5: Action (coordinate, build, borrow, keep) | O5: Owner
A6: =IF('2 Competency Spine'!A6="","",'2 Competency Spine'!A6) -> C-01 | B6: =IF('2 Competency Spine'!C6="","",'2 Competency Spine'!C6) -> Communication | C6: =IF('2 Competency Spine'!B6="","",'2 Competency Spine'!B6) -> Core | D6: =IF('2 Competency Spine'!E6="","",'2 Competency Spine'!E6) -> All pathways | E6: =IF('2 Competency Spine'!O6="","",'2 Competency Spine'!O6) -> MNT140 | F6: =IF(TRIM(E6)="",0,LEN(E6)-LEN(SUBSTITUTE(E6,"/",""))+1) -> 1 | G6: =IF(A6="","",IF(OR('2 Competency Spine'!M6<>"",'2 Competency Spine'!N6<>""),"Yes","No")) -> Yes | H6: ='2 Competency Spine'!S6 -> 4 | I6: =IF(A6="","",IF(H6=0,"Gap: not taught anywhere",IF(F6=0,"Gap: no community college offering",IF(F6>1,"Check: multiple CC courses",IF(G6="No","Covered: no high school on-ramp","Covered"))))) -> Covered | M6: =IF(LEFT(I6,5)<>"Check","",IF(COUNTIF(J6:L6,"Yes")+COUNTIF(J6:L6,"No")<3,"Answer the 3 questions",IF(COUNTIF(J6:L6,"Yes")=3,"Duplication: coordinate","Healthy on-ramp: keep")))
A7: =IF('2 Competency Spine'!A7="","",'2 Competency Spine'!A7) -> C-02 | B7: =IF('2 Competency Spine'!C7="","",'2 Competency Spine'!C7) -> Collaboration | C7: =IF('2 Competency Spine'!B7="","",'2 Competency Spine'!B7) -> Core | D7: =IF('2 Competency Spine'!E7="","",'2 Competency Spine'!E7) -> All pathways | E7: =IF('2 Competency Spine'!O7="","",'2 Competency Spine'!O7) -> MNT140 | F7: =IF(TRIM(E7)="",0,LEN(E7)-LEN(SUBSTITUTE(E7,"/",""))+1) -> 1 | G7: =IF(A7="","",IF(OR('2 Competency Spine'!M7<>"",'2 Competency Spine'!N7<>""),"Yes","No")) -> Yes | H7: ='2 Competency Spine'!S7 -> 4 | I7: =IF(A7="","",IF(H7=0,"Gap: not taught anywhere",IF(F7=0,"Gap: no community college offering",IF(F7>1,"Check: multiple CC courses",IF(G7="No","Covered: no high school on-ramp","Covered"))))) -> Covered | M7: =IF(LEFT(I7,5)<>"Check","",IF(COUNTIF(J7:L7,"Yes")+COUNTIF(J7:L7,"No")<3,"Answer the 3 questions",IF(COUNTIF(J7:L7,"Yes")=3,"Duplication: coordinate","Healthy on-ramp: keep")))
A8: =IF('2 Competency Spine'!A8="","",'2 Competency Spine'!A8) -> C-03 | B8: =IF('2 Competency Spine'!C8="","",'2 Competency Spine'!C8) -> Digital Fluency | C8: =IF('2 Competency Spine'!B8="","",'2 Competency Spine'!B8) -> Core | D8: =IF('2 Competency Spine'!E8="","",'2 Competency Spine'!E8) -> All pathways | E8: =IF('2 Competency Spine'!O8="","",'2 Competency Spine'!O8) -> AIT132 | F8: =IF(TRIM(E8)="",0,LEN(E8)-LEN(SUBSTITUTE(E8,"/",""))+1) -> 1 | G8: =IF(A8="","",IF(OR('2 Competency Spine'!M8<>"",'2 Competency Spine'!N8<>""),"Yes","No")) -> Yes | H8: ='2 Competency Spine'!S8 -> 4 | I8: =IF(A8="","",IF(H8=0,"Gap: not taught anywhere",IF(F8=0,"Gap: no community college offering",IF(F8>1,"Check: multiple CC courses",IF(G8="No","Covered: no high school on-ramp","Covered"))))) -> Covered | M8: =IF(LEFT(I8,5)<>"Check","",IF(COUNTIF(J8:L8,"Yes")+COUNTIF(J8:L8,"No")<3,"Answer the 3 questions",IF(COUNTIF(J8:L8,"Yes")=3,"Duplication: coordinate","Healthy on-ramp: keep")))
A9: =IF('2 Competency Spine'!A9="","",'2 Competency Spine'!A9) -> C-04 | B9: =IF('2 Competency Spine'!C9="","",'2 Competency Spine'!C9) -> Critical Thinking & Problem Solving | C9: =IF('2 Competency Spine'!B9="","",'2 Competency Spine'!B9) -> Core | D9: =IF('2 Competency Spine'!E9="","",'2 Competency Spine'!E9) -> All pathways | E9: =IF('2 Competency Spine'!O9="","",'2 Competency Spine'!O9) -> AIT132 | F9: =IF(TRIM(E9)="",0,LEN(E9)-LEN(SUBSTITUTE(E9,"/",""))+1) -> 1 | G9: =IF(A9="","",IF(OR('2 Competency Spine'!M9<>"",'2 Competency Spine'!N9<>""),"Yes","No")) -> Yes | H9: ='2 Competency Spine'!S9 -> 4 | I9: =IF(A9="","",IF(H9=0,"Gap: not taught anywhere",IF(F9=0,"Gap: no community college offering",IF(F9>1,"Check: multiple CC courses",IF(G9="No","Covered: no high school on-ramp","Covered"))))) -> Covered | M9: =IF(LEFT(I9,5)<>"Check","",IF(COUNTIF(J9:L9,"Yes")+COUNTIF(J9:L9,"No")<3,"Answer the 3 questions",IF(COUNTIF(J9:L9,"Yes")=3,"Duplication: coordinate","Healthy on-ramp: keep")))
A10: =IF('2 Competency Spine'!A10="","",'2 Competency Spine'!A10) -> C-05 | B10: =IF('2 Competency Spine'!C10="","",'2 Competency Spine'!C10) -> Numeracy | C10: =IF('2 Competency Spine'!B10="","",'2 Competency Spine'!B10) -> Core | D10: =IF('2 Competency Spine'!E10="","",'2 Competency Spine'!E10) -> All pathways | E10: =IF('2 Competency Spine'!O10="","",'2 Competency Spine'!O10) -> MNT235 | F10: =IF(TRIM(E10)="",0,LEN(E10)-LEN(SUBSTITUTE(E10,"/",""))+1) -> 1 | G10: =IF(A10="","",IF(OR('2 Competency Spine'!M10<>"",'2 Competency Spine'!N10<>""),"Yes","No")) -> Yes | H10: ='2 Competency Spine'!S10 -> 4 | I10: =IF(A10="","",IF(H10=0,"Gap: not taught anywhere",IF(F10=0,"Gap: no community college offering",IF(F10>1,"Check: multiple CC courses",IF(G10="No","Covered: no high school on-ramp","Covered"))))) -> Covered | M10: =IF(LEFT(I10,5)<>"Check","",IF(COUNTIF(J10:L10,"Yes")+COUNTIF(J10:L10,"No")<3,"Answer the 3 questions",IF(COUNTIF(J10:L10,"Yes")=3,"Duplication: coordinate","Healthy on-ramp: keep")))
A11: =IF('2 Competency Spine'!A11="","",'2 Competency Spine'!A11) -> C-06 | B11: =IF('2 Competency Spine'!C11="","",'2 Competency Spine'!C11) -> Reading & Writing | C11: =IF('2 Competency Spine'!B11="","",'2 Competency Spine'!B11) -> Core | D11: =IF('2 Competency Spine'!E11="","",'2 Competency Spine'!E11) -> All pathways | E11: =IF('2 Competency Spine'!O11="","",'2 Competency Spine'!O11) -> ENG101 | F11: =IF(TRIM(E11)="",0,LEN(E11)-LEN(SUBSTITUTE(E11,"/",""))+1) -> 1 | G11: =IF(A11="","",IF(OR('2 Competency Spine'!M11<>"",'2 Competency Spine'!N11<>""),"Yes","No")) -> Yes | H11: ='2 Competency Spine'!S11 -> 4 | I11: =IF(A11="","",IF(H11=0,"Gap: not taught anywhere",IF(F11=0,"Gap: no community college offering",IF(F11>1,"Check: multiple CC courses",IF(G11="No","Covered: no high school on-ramp","Covered"))))) -> Covered | M11: =IF(LEFT(I11,5)<>"Check","",IF(COUNTIF(J11:L11,"Yes")+COUNTIF(J11:L11,"No")<3,"Answer the 3 questions",IF(COUNTIF(J11:L11,"Yes")=3,"Duplication: coordinate","Healthy on-ramp: keep")))
A12: =IF('2 Competency Spine'!A12="","",'2 Competency Spine'!A12) -> K-01 | B12: =IF('2 Competency Spine'!C12="","",'2 Competency Spine'!C12) -> Interpret basic electrical & circuit concepts & diagrams | C12: =IF('2 Competency Spine'!B12="","",'2 Competency Spine'!B12) -> Cluster | D12: =IF('2 Competency Spine'!E12="","",'2 Competency Spine'!E12) -> All pathways | E12: =IF('2 Competency Spine'!O12="","",'2 Competency Spine'!O12) -> AIT132 | F12: =IF(TRIM(E12)="",0,LEN(E12)-LEN(SUBSTITUTE(E12,"/",""))+1) -> 1 | G12: =IF(A12="","",IF(OR('2 Competency Spine'!M12<>"",'2 Competency Spine'!N12<>""),"Yes","No")) -> Yes | H12: ='2 Competency Spine'!S12 -> 4 | I12: =IF(A12="","",IF(H12=0,"Gap: not taught anywhere",IF(F12=0,"Gap: no community college offering",IF(F12>1,"Check: multiple CC courses",IF(G12="No","Covered: no high school on-ramp","Covered"))))) -> Covered | M12: =IF(LEFT(I12,5)<>"Check","",IF(COUNTIF(J12:L12,"Yes")+COUNTIF(J12:L12,"No")<3,"Answer the 3 questions",IF(COUNTIF(J12:L12,"Yes")=3,"Duplication: coordinate","Healthy on-ramp: keep")))
A13: =IF('2 Competency Spine'!A13="","",'2 Competency Spine'!A13) -> K-02 | B13: =IF('2 Competency Spine'!C13="","",'2 Competency Spine'!C13) -> Use AI and ML tools to optimize manufacturing | C13: =IF('2 Competency Spine'!B13="","",'2 Competency Spine'!B13) -> Cluster | D13: =IF('2 Competency Spine'!E13="","",'2 Competency Spine'!E13) -> All pathways | E13: =IF('2 Competency Spine'!O13="","",'2 Competency Spine'!O13) -> AIM230 | F13: =IF(TRIM(E13)="",0,LEN(E13)-LEN(SUBSTITUTE(E13,"/",""))+1) -> 1 | G13: =IF(A13="","",IF(OR('2 Competency Spine'!M13<>"",'2 Competency Spine'!N13<>""),"Yes","No")) -> Yes | H13: ='2 Competency Spine'!S13 -> 4 | I13: =IF(A13="","",IF(H13=0,"Gap: not taught anywhere",IF(F13=0,"Gap: no community college offering",IF(F13>1,"Check: multiple CC courses",IF(G13="No","Covered: no high school on-ramp","Covered"))))) -> Covered | M13: =IF(LEFT(I13,5)<>"Check","",IF(COUNTIF(J13:L13,"Yes")+COUNTIF(J13:L13,"No")<3,"Answer the 3 questions",IF(COUNTIF(J13:L13,"Yes")=3,"Duplication: coordinate","Healthy on-ramp: keep")))
A14: =IF('2 Competency Spine'!A14="","",'2 Competency Spine'!A14) -> K-03 | B14: =IF('2 Competency Spine'!C14="","",'2 Competency Spine'!C14) -> Use SPC charts and data tools to monitor processes | C14: =IF('2 Competency Spine'!B14="","",'2 Competency Spine'!B14) -> Cluster | D14: =IF('2 Competency Spine'!E14="","",'2 Competency Spine'!E14) -> All pathways | E14: =IF('2 Competency Spine'!O14="","",'2 Competency Spine'!O14) -> MNT108 | F14: =IF(TRIM(E14)="",0,LEN(E14)-LEN(SUBSTITUTE(E14,"/",""))+1) -> 1 | G14: =IF(A14="","",IF(OR('2 Competency Spine'!M14<>"",'2 Competency Spine'!N14<>""),"Yes","No")) -> Yes | H14: ='2 Competency Spine'!S14 -> 4 | I14: =IF(A14="","",IF(H14=0,"Gap: not taught anywhere",IF(F14=0,"Gap: no community college offering",IF(F14>1,"Check: multiple CC courses",IF(G14="No","Covered: no high school on-ramp","Covered"))))) -> Covered | M14: =IF(LEFT(I14,5)<>"Check","",IF(COUNTIF(J14:L14,"Yes")+COUNTIF(J14:L14,"No")<3,"Answer the 3 questions",IF(COUNTIF(J14:L14,"Yes")=3,"Duplication: coordinate","Healthy on-ramp: keep")))
A15: =IF('2 Competency Spine'!A15="","",'2 Competency Spine'!A15) -> K-04 | B15: =IF('2 Competency Spine'!C15="","",'2 Competency Spine'!C15) -> Recognize & respond to physical security & cybersecurity risks | C15: =IF('2 Competency Spine'!B15="","",'2 Competency Spine'!B15) -> Cluster | D15: =IF('2 Competency Spine'!E15="","",'2 Competency Spine'!E15) -> All pathways | E15: =IF('2 Competency Spine'!O15="","",'2 Competency Spine'!O15) -> CIS270 / ITS110 | F15: =IF(TRIM(E15)="",0,LEN(E15)-LEN(SUBSTITUTE(E15,"/",""))+1) -> 2 | G15: =IF(A15="","",IF(OR('2 Competency Spine'!M15<>"",'2 Competency Spine'!N15<>""),"Yes","No")) -> Yes | H15: ='2 Competency Spine'!S15 -> 4 | I15: =IF(A15="","",IF(H15=0,"Gap: not taught anywhere",IF(F15=0,"Gap: no community college offering",IF(F15>1,"Check: multiple CC courses",IF(G15="No","Covered: no high school on-ramp","Covered"))))) -> Check: multiple CC courses | M15: =IF(LEFT(I15,5)<>"Check","",IF(COUNTIF(J15:L15,"Yes")+COUNTIF(J15:L15,"No")<3,"Answer the 3 questions",IF(COUNTIF(J15:L15,"Yes")=3,"Duplication: coordinate","Healthy on-ramp: keep"))) -> Answer the 3 questions
A16: =IF('2 Competency Spine'!A16="","",'2 Competency Spine'!A16) -> K-05 | B16: =IF('2 Competency Spine'!C16="","",'2 Competency Spine'!C16) -> Follow OSHA, COHE, & cleanroom safety protocols | C16: =IF('2 Competency Spine'!B16="","",'2 Competency Spine'!B16) -> Cluster | D16: =IF('2 Competency Spine'!E16="","",'2 Competency Spine'!E16) -> All pathways | E16: =IF('2 Competency Spine'!O16="","",'2 Competency Spine'!O16) -> MNT201 | F16: =IF(TRIM(E16)="",0,LEN(E16)-LEN(SUBSTITUTE(E16,"/",""))+1) -> 1 | G16: =IF(A16="","",IF(OR('2 Competency Spine'!M16<>"",'2 Competency Spine'!N16<>""),"Yes","No")) -> Yes | H16: ='2 Competency Spine'!S16 -> 4 | I16: =IF(A16="","",IF(H16=0,"Gap: not taught anywhere",IF(F16=0,"Gap: no community college offering",IF(F16>1,"Check: multiple CC courses",IF(G16="No","Covered: no high school on-ramp","Covered"))))) -> Covered | M16: =IF(LEFT(I16,5)<>"Check","",IF(COUNTIF(J16:L16,"Yes")+COUNTIF(J16:L16,"No")<3,"Answer the 3 questions",IF(COUNTIF(J16:L16,"Yes")=3,"Duplication: coordinate","Healthy on-ramp: keep")))
A17: =IF('2 Competency Spine'!A17="","",'2 Competency Spine'!A17) -> K-06 | B17: =IF('2 Competency Spine'!C17="","",'2 Competency Spine'!C17) -> Diagnose issues in semiconductor tools & systems | C17: =IF('2 Competency Spine'!B17="","",'2 Competency Spine'!B17) -> Cluster | D17: =IF('2 Competency Spine'!E17="","",'2 Competency Spine'!E17) -> All pathways | E17: =IF('2 Competency Spine'!O17="","",'2 Competency Spine'!O17) -> AIT132 | F17: =IF(TRIM(E17)="",0,LEN(E17)-LEN(SUBSTITUTE(E17,"/",""))+1) -> 1 | G17: =IF(A17="","",IF(OR('2 Competency Spine'!M17<>"",'2 Competency Spine'!N17<>""),"Yes","No")) -> Yes | H17: ='2 Competency Spine'!S17 -> 4 | I17: =IF(A17="","",IF(H17=0,"Gap: not taught anywhere",IF(F17=0,"Gap: no community college offering",IF(F17>1,"Check: multiple CC courses",IF(G17="No","Covered: no high school on-ramp","Covered"))))) -> Covered | M17: =IF(LEFT(I17,5)<>"Check","",IF(COUNTIF(J17:L17,"Yes")+COUNTIF(J17:L17,"No")<3,"Answer the 3 questions",IF(COUNTIF(J17:L17,"Yes")=3,"Duplication: coordinate","Healthy on-ramp: keep")))
... A95: =IF('2 Competency Spine'!A95="","",'2 Competency Spine'!A95) -> PEQ-15 | B95: =IF('2 Competency Spine'!C95="","",'2 Competency Spine'!C95) -> Design of experiments | C95: =IF('2 Competency Spine'!B95="","",'2 Competency Spine'!B95) -> Pathway | D95: =IF('2 Competency Spine'!E95="","",'2 Competency Spine'!E95) -> Process Engineering & Quality | E95: =IF('2 Competency Spine'!O95="","",'2 Competency Spine'!O95) -> GTC108 / SEM210 | F95: =IF(TRIM(E95)="",0,LEN(E95)-LEN(SUBSTITUTE(E95,"/",""))+1) -> 2 | G95: =IF(A95="","",IF(OR('2 Competency Spine'!M95<>"",'2 Competency Spine'!N95<>""),"Yes","No")) -> No | H95: ='2 Competency Spine'!S95 -> 3 | I95: =IF(A95="","",IF(H95=0,"Gap: not taught anywhere",IF(F95=0,"Gap: no community college offering",IF(F95>1,"Check: multiple CC courses",IF(G95="No","Covered: no high school on-ramp","Covered"))))) -> Check: multiple CC courses | M95: =IF(LEFT(I95,5)<>"Check","",IF(COUNTIF(J95:L95,"Yes")+COUNTIF(J95:L95,"No")<3,"Answer the 3 questions",IF(COUNTIF(J95:L95,"Yes")=3,"Duplication: coordinate","Healthy on-ramp: keep"))) -> Answer the 3 questions

Sheet 5 Entry Points
A1: Step 5 · Open multiple entry points
A2: Many doors onto one pathway. List the stops first (each with job value), then the doors and how credit connects so no learning is wasted.
A3: Legend: cream cells = your input · gray cells = calculated (don’t edit) · “Example” rows show the Arizona worked example; overwrite them.
A5: Stops on the pathway
A6: Stop | B6: Credential | C6: Job value: roles it qualifies for | D6: Competency IDs credited (from spine) | E6: Next stop | F6: Notes
A7: CCL-1 | B7: Entry certificate | E7: CCL-2
A8: CCL-2 | B8: Advanced certificate | E8: AAS
A9: AAS | B9: Associate degree | E9: Bachelor’s
A10: Bachelor’s | B10: Bachelor’s completion via NAU articulation
A15: Doors onto the pathway
A16: Door | B16: Who it serves | C16: Enters at (stop) | D16: Credit connection | E16: Offering(s) | F16: Lead partner | G16: Status | H16: Notes
A17: Example: High school students | B17: Dual enrollment students | C17: CCL-1 | D17: Dual enrollment | E17: Same industry-endorsed semiconductor manufacturing certificate | F17: High school + college
A18: Example: Adults new to the field | B18: Students starting from scratch | C18: CCL-1 | D18: Direct enrollment | E18: Entry certificate, beginning with the industry-overview course | F18: College
A19: Example: Apprentices | B19: Employer-sponsored apprentices | C19: CCL-1 | D19: Apprenticeship RTI crosswalk | E19: TSMC apprenticeship RTI crosswalk | F19: Employer + college
A20: Example: Working adults and career changers | B20: Incumbent workers; people with related experience | C20: CCL-1 | D20: Prior learning assessment | E20: Accelerated non-credit equipment training mapped to credit | F20: College
A21: Example: Transfer-bound students | B21: AAS graduates seeking a bachelor’s | C21: Bachelor’s | D21: Articulation | E21: NAU articulation | F21: University + college
A27: Every door should count toward the next stop, and every stop should lead to a job.

Sheet Summary
A1: Summary
A2: Updates as you fill in the other sheets.
A5: Competency spine
A6: Competencies on the spine | B6: =COUNTIF('2 Competency Spine'!B6:B155,"Core")+COUNTIF('2 Competency Spine'!B6:B155,"Cluster")+COUNTIF('2 Competency Spine'!B6:B155,"Pathway") -> 90
A7: Core | B7: =COUNTIF('2 Competency Spine'!B6:B155,"Core") -> 6
A8: Cluster | B8: =COUNTIF('2 Competency Spine'!B6:B155,"Cluster") -> 11
A9: Pathway | B9: =COUNTIF('2 Competency Spine'!B6:B155,"Pathway") -> 73
A11: Overlaps and gaps
A12: Gap: not taught anywhere | B12: =COUNTIF('4 Overlap and Gaps'!I6:I95,"Gap: not taught anywhere") -> 0
A13: Gap: no community college offering | B13: =COUNTIF('4 Overlap and Gaps'!I6:I95,"Gap: no community college offering") -> 0
A14: Check: multiple CC courses | B14: =COUNTIF('4 Overlap and Gaps'!I6:I95,"Check: multiple CC courses") -> 46
A15: of which, duplication to coordinate | B15: =COUNTIF('4 Overlap and Gaps'!M6:M95,"Duplication: coordinate") -> 0
A16: Covered: no high school on-ramp | B16: =COUNTIF('4 Overlap and Gaps'!I6:I95,"Covered: no high school on-ramp") -> 7
A17: Covered | B17: =COUNTIF('4 Overlap and Gaps'!I6:I95,"Covered") -> 37
A18: Taught in only one layer or none | B18: =COUNTIF('2 Competency Spine'!S6:S95,"<=1") -> 0
A20: Partners
A21: Functions with no lead | B21: =COUNTIF('3 Partner Roles'!K7:K19,"No lead") -> 0
A22: Functions with multiple leads | B22: =COUNTIF('3 Partner Roles'!K7:K19,"Multiple leads: clarify") -> 1
A24: Entry points
A25: Stops defined | B25: =COUNTA('5 Entry Points'!A7:A12) -> 4
A26: Doors defined | B26: =COUNTA('5 Entry Points'!A17:A25) -> 5
A27: Doors live | B27: =COUNTIF('5 Entry Points'!G17:G25,"Live") -> 0

Sheet Source Crosswalk
A1: Source: SciTech Institute Semiconductor Manufacturing Skills Crosswalk (copied as provided, for reference; edit the spine, not this sheet).
B3: Skill Category | C3: Domain | D3: O*Net Code | E3: CIP Code | F3: ADE Standard(s) | G3: Supporting ADE Standard Text | H3: MCCCD Course Code | I3: Supporting MCCCD Standard Text | J3: UA Course Code | K3: Supporting UA Standard Text | L3: Chip Path Courses | M3: Chip Path Supporting Text | N3: PLTW Courses | O3: Supporting PLTW Text | P3: 17-3023.00 (Electrical & Electronic Engineering Technologists & Techs) | Q3: 15-1231.00 (Computer Network Support Specialists) | R3: 49-9071.00 (Maintenance & Repair Workers, General) | S3: 17-2199.00 (Engineers, All Other / Mechatronics & Microsystems)
A4: CORE
A5: Communication | F5: 7.13 | G5: 7.13 Communicate technical information clearly using basic text and visual tools (e.g., PowerPoint presentations) | H5: MNT140 | I5: The program prepares students with the foundational expectations for interpersonal and professional skills within the industry. | J5: CHEE 415 / SIE 465 | K5: CHEE 415 connects semiconductor manufacturing processes with environmental implications, a context that requires communicating technical, regulatory, and operational considerations across disciplines. SIE 465 situates students in supply-chain decisions that typically require clear coordination among engineering, operations, suppliers, and customers. The co-curricular Fast Track explicitly includes an employer panel and final team presentations to industry partners, making it the clearest published communication-focused experience. | L5: CP-101 | M5: Articulates ideas clearly and effectively in written, verbal, and technical formats within multidisciplinary manufacturing environments. | N5: PLTW Engineering (EDD, IED) | O5: Students deliver oral technical presentations to panels of engineering professionals, generate standard CAD drawings, and present complex scientific concepts to non-technical stakeholders. | P5: Communicating with Supervisors, Peers, or Subordinates — Provide information to supervisors, co-workers, and subordinates by telephone, written form, email, or in person. | Q5: Answer user inquiries regarding computer software or hardware operation to resolve problems; explain resolution steps to technical and non-technical staff. | R5: Communicate with machine operators, tenants, or supervisors to discuss equipment performance, facility needs, and repair timelines. | S5: Present technical reports, design specifications, and operational recommendations to clients, engineering teams, and executive management.
F6: 1.7 | G6: 1.7 Summarize basic knowledge and skills needed by all levels of semiconductor workers (... cross-functional communication skills...) | N6: PLTW Biomedical Science (BI)
F7: 7.5 | G7: 7.5 (... explain yield in simple terms during a team discussion, etc.) | N7: PLTW Gateway (DM)
F8: 7.2 | G8: 7.2 Explain diagrams and basic technical drawings to understand equipment, processes, and systems (i.e., process flow diagrams, equipment schematics, simple system layouts, etc.)
F9: 11.2 | G9: 11.2 Describe how the authentication, authorization and accounting (AAA) security framework is used to manage network access, enforce policies, and monitor user activity
F10: 1.8 | G10: 1.8 Discuss overall education and training and career pathways for workers in the semiconductor industry...
A11: Collaboration | F11: 2.8 | G11: 2.8 Follow cleanroom protocol, housekeeping procedures, and standardized work practices to maintain safety, cleanliness, and product quality (i.e., proper gowning and de-gowning...) | H11: MNT140 | I11: The program prepares students with the foundational expectations for interpersonal and professional skills within the industry. | J11: MSE/ECE 447/ SIE 483 | K11: The processing laboratory provides hands-on semiconductor/MEMS processing experience, which supports coordinated lab work, shared procedures, documentation, and safety/quality practices. Computer-integrated manufacturing links engineering systems and production operations. The Fast Track requires students to complete a team project and present it to industry partners, directly demonstrating collaborative work. | L11: CP-102 | M11: Works productively in diverse teams, sharing responsibilities and coordinating tasks to achieve common project and production goals. | N11: PLTW Engineering (POE, CIM) | O11: Multidisciplinary student teams implement project management frameworks, division of labor (e.g., project manager, lead designer, test technician), peer design reviews, and collaborative technical troubleshooting. | P11: Work in operational teams with engineers, production personnel, and technicians to assemble, test, and refine electronic systems. | Q11: Coordinate with network administrators, vendors, and IT team members to resolve complex system outages and implementation issues. | R11: Collaborate with specialized contractors, building managers, and maintenance teams on facility overhauls and major repairs. | S11: Collaborate with multidisciplinary engineering teams (mechanical, software, systems) to design and integrate automated components.
N12: PLTW Computer Science (SEC)
N13: PLTW Gateway (AR)
A14: Digital Fluency | F14: 7.12 | G14: 7.12 Use basic software tools to view, enter, and understand production or process data (i.e., enter data into a digital log or form... understand basic python scripting, etc.) | H14: AIT132 | I14: The Industrial Technology for Semiconductor certificate includes instruction in “digital fundamentals,” along with AC/DC circuits, solid-state devices, industrial electronics, quality assurance, and semiconductor manufacturing technology. | J14: ECE 407/SIE 483/MSE 480 | K14: ECE 407 addresses digital VLSI system design, aligning with fluency in digital logic/design tools and electronic-system concepts. SIE 483 focuses on computer-integrated manufacturing systems, supporting familiarity with digitally enabled production environments. MSE 480’s emphasis on advanced characterization methods supports interpreting instrument-generated materials data and working with sophisticated technical equipment. | L14: CP-103 | M14: Demonstrates proficiency in navigating digital tools, automated control systems, data entry platforms, and industry-standard software interfaces. | N14: PLTW Engineering (IED, DE, CIM) | O14: Students operate industry-standard software tools (CAD, circuit simulation environments, Python/Java IDEs, G-code software) and physical hardware (3D printers, CNC equipment, microcontrollers, and sensors). | P14: Utilize CAD software, circuit simulation tools (e.g., SPICE), diagnostic software, and computer-based testing interfaces. | Q14: Operate network diagnostic utilities, terminal emulation software, operating system administration tools, and ticketing software. | R14: Utilize Computerized Maintenance Management Systems (CMMS) and digital building automation/HVAC control interfaces. | S14: Apply specialized engineering software (MATLAB, LabVIEW, CAD/CAM), system simulation tools, and embedded system programming environments.
N15: PLTW Computer Science (CSE, CSA, SEC)
F16: 11.1 | G16: 11.1 Distinguish between physical security and cybersecurity (e.g., physical security protects tangible assets like buildings and hardware, and cybersecurity defends digital assets like networks and data) | N16: PLTW Gateway (AC)
A17: Critical Thinking & Problem Solving | F17: 7.1 | G17: 7.1 Read and interpret basic control charts to determine whether a process is operating normally or outside expected limits. | H17: AIT132 | I17: The Industrial Technology for Semiconductor certificate requires students to “apply knowledge of basic semiconductor manufacturing concepts and processes, basic industrial electrical principles, schematics, circuits, hand tools, and appropriate problem-solving models to troubleshoot and address problems in the semiconductor industry.” It also requires students to apply vacuum components, procedures, theory, and tools to “efficiently and effectively troubleshoot common issues found in a system under vacuum.” | J17: MSE/ECE 447/547 | K17: The laboratory course adds applied troubleshooting in semiconductor/MEMS processing. Quality and reliability engineering provide frameworks for analyzing variation, defects, performance, and failure risk. | L17: CP-104 | M17: Analyzes complex process data, identifies root causes of technical anomalies, and implements logical, efficient troubleshooting solutions. | N17: PLTW Engineering (IED, POE, EDD) | O17: Students apply the open-ended PLTW Design Process (Define, Imagine, Design, Create, Test, Evaluate) to diagnose physical/digital system failures, evaluate trade-offs, and iteratively refine designs based on test data. | P17: Critical Thinking — Using logic and reasoning to identify the strengths and weaknesses of alternative solutions, conclusions, or approaches to problems. | Q17: Troubleshooting — Determining causes of operating errors and deciding what to do about them; analyze diagnostic output to resolve network failures. | R17: Inspect, operate, or test machinery to diagnose machine malfunctions; evaluate repair options to determine the most cost-effective solution. | S17: Complex Problem Solving — Identifying complex problems and reviewing related information to develop and evaluate options and implement solutions.
F18: 8.3 | G18: 8.3 Describe basic advantages and limitations of sensors used in manufacturing systems (i.e., size, speed, reliability, need for calibration, drift over time, etc.) | N18: PLTW Biomedical Science (PBS, MI)
F19: 5.12 | G19: 5.12 Troubleshoot piping components and piping systems, pumps, valves, pneumatic and hydraulic components and systems, and heat exchangers | N19: PLTW Gateway (MD)
F20: 2.5 | G20: 2.5 Identify safety procedures when working around automated and robotic systems (i.e., adhere to restricted zones, respond appropriately to alarms...)
F21: 9.5/9.6 | G21: 9.5 / 9.6 Use systematic problem-solving techniques [i.e., root cause and corrective action (RCCA)...] / Explain the basics of standard operating procedures (SOPs)...
A22: Numeracy | F22: 7.4 | G22: 7.4 Apply basic math and unit conversions to support measurements, trends, and simple calculations used in manufacturing environments (i.e., averages, percentages, limits, unit conversions, etc.) | H22: MNT235 | I22: “Covers measurement science, statistical process control, inspection methodologies, measurement system analysis, and failure analysis techniques.” The description also emphasizes “yield optimization, measurement uncertainty, calibration procedures, and implementation of quality control protocols.” | J22: SIE 305/SIE 430 | K22: The minor’s foundational chemistry options include quantitatively oriented coursework. SIE 305 introduces engineering probability and statistics, and SIE 430 builds statistical capability for engineering applications. Together, these courses support measurement, quantitative reasoning, process-data analysis, variation analysis, and evidence-based manufacturing decisions. | L22: CP-105 | M22: Applies mathematical principles, statistical process control, and precise measurement skills to interpret technical specifications and metrics. | N22: PLTW Engineering (POE, DE, IED) | O22: Students calculate force vectors, electrical circuit values (Ohm's/Kirchhoff's Laws), dimensional tolerances using dial calipers, unit conversions, and statistical distribution metrics (mean, standard deviation) from experimental data. | P22: Calculate basic electrical properties (voltage, current, resistance, capacitance) using mathematical formulas, Ohm's law, and algebra. | Q22: Compute network subnet masks, IP address allocations, bandwidth consumption, data transfer rates, and system uptime percentages. | R22: Measure dimensions, calculate surface areas/volumes, compute material quantities, and estimate labor and material costs for maintenance work. | S22: Mathematics — Using mathematics to solve problems; apply advanced principles of calculus, statistics, and linear algebra to system design and yield analysis.
N23: PLTW Biomedical Science (HBS, MI)
N24: PLTW Computer Science (CSA)
A25: Reading & Writing | F25: 11.6/11.7 | G25: 11.6 / 11.7 Identify protocols for cybersecurity threats / Identify protocols for protecting intellectual property | H25: ENG101 | I25: The Semiconductor Manufacturing AAS includes a general-education foundation, and MCCCD identifies Written Communication (WCM) as a course-designation area. ENG101 is the district’s foundational composition course within that requirement structure | J25: CHEE 415 | K25: CHEE 415 adds an applied context for explaining manufacturing-related environmental issues in writing. | L25: CP-106 | M25: Accurately interprets technical manuals, standard operating procedures (SOPs), and schematics while producing clear technical documentation and logs. | N25: PLTW Engineering (All, esp. EDD, IED) | O25: Students maintain legal-grade Engineering Notebooks, conduct academic literature and patent searches, interpret technical specification sheets/schematics, and author formal design proposals and lab reports. | P25: Read and interpret schematics, blueprints, and technical manuals; write test reports, system logs, and standard operating procedures (SOPs). | Q25: Read technical documentation, error logs, and vendor manuals; document network troubleshooting steps, resolution procedures, and user guides. | R25: Read blueprints, building diagrams, electrical schematics, and equipment manuals; maintain written maintenance logs and work orders. | S25: Read technical papers, regulatory compliance standards, and patent specifications; write formal engineering specifications and technical reports.
F26: 2.8 | G26: 2.8 Follow cleanroom protocol... (i.e., documenting issues and near misses, reporting spills, damage, or injuries, etc.) | N26: PLTW Biomedical Science (PBS, BI)
N27: PLTW Computer Science (SEC)
A28: CLUSTER
A29: Interpret basic electrical & circuit concepts & diagrams | B29: Technical Foundations | C29: NA | D29: NA | E29: NA | F29: 6.1-6.4; 7.2 | G29: 6.1-6.4 cover voltage/current/resistance, Ohm's & Kirchhoff's Laws, doping, diodes/transistors/ICs; 7.2 covers schematics and system diagrams. | H29: AIT132 | I29: Program content “includes instruction in AC and DC circuits, digital fundamentals, solid state devices, industrial electronics, and semiconductor manufacturing technology.” | J29: ECE 220 | K29: Covers fundamental AC/DC circuit analysis, Kirchhoff’s laws, operational amplifiers, semiconductor diode/transistor modeling, and reading electrical schematics. | L29: CP-101 / ELC-101 | M29: Analyzes direct and alternating current principles, interprets electrical schematics, reads logic diagrams, and applies Ohm's/Kirchhoff's Laws to circuit diagnostics. | N29: PLTW Engineering (DE, POE) | O29: Students calculate voltage, current, and resistance using Ohm's and Kirchhoff's Laws, design and simulate digital circuit schematics, and construct physical circuits using breadboards and logic components. | P29: Read blueprints, wiring diagrams, schematic drawings, or engineering instructions for assembling electronics units. | Q29: Install or repair network cables, including fiber optic cables. | R29: Plan and lay out repair work, using diagrams, drawings, blueprints, maintenance manuals, or schematic diagrams. | S29: Create schematics and physical layouts of integrated microelectromechanical systems (MEMS); design control circuits.
A30: Use AI and ML tools to optimize manufacturing | B30: Data, Analysis, & Digital Tools | C30: NA | D30: NA | E30: NA | F30: 7.9 | G30: 7.9: “Explain how AI and ML are used in semiconductor manufacturing...to improve manufacturing yields, to improve overall efficiency.” | H30: AIM230 | I30: Explores business and operational integration of AI. Emphasizes leveraging AI/ML tools to streamline supply chains, optimize high-tech factory workflows, reduce operational overhead, and solve industrial scaling challenges. | J30: SIE 574 | K30: Teaches predictive modeling, supervised/unsupervised machine learning, and AI algorithms applied to complex industrial systems and manufacturing optimization. | L30: CP-103 / DAT-110 | M30: Utilizes predictive machine learning algorithms, automated data models, and AI-driven process optimization tools to increase yield and reduce equipment downtime. | N30: PLTW Computer Science (CSE, CSA) | O30: Students utilize Python libraries (e.g., NumPy, Pandas, Scikit-learn) to train machine learning models for predictive analysis, process optimization, and automated decision-making. | P30: Select tools, equipment, or technologies for use in operations or projects; operate computer systems. | Q30: Update knowledge about emerging industry or technology trends; troubleshoot computer systems. | R30: Adjust equipment to ensure optimal performance. | S30: Research, design, develop, or test automation, intelligent systems, smart devices, or industrial systems control.
A31: Use SPC charts and data tools to monitor processes | B31: Data, Analysis, & Digital Tools | C31: NA | D31: NA | E31: NA | F31: 7.1; 9.7 | G31: 7.1 covers reading/interpreting control charts; 9.7: “Explain the basics of Statistical Process Control (SPC) to monitor, control, and improve production processes.” | H31: MNT108 | I31: Focuses directly on the principles and applications of Statistical Process Control (SPC) in semiconductor production. Program learning outcomes specifically require students to "Analyze quality control methods including statistical process control (SPC) through the use of metrology techniques and tools to support quality in semiconductor manufacturing operations." | J31: SIE 540 | K31: Focuses on Statistical Process Control (SPC), control charting (X-bar, R, p-charts), process capability analysis ($C_p$/$C_{pk}$), and design of experiments (DOE) for quality assurance. | L31: CP-103 / GTC-108 | M31: Constructs, reads, and interprets Statistical Process Control (SPC) charts (X-bar, R-charts), monitors trend rules, and uses data software to keep processes within tolerance limits. | N31: PLTW Engineering (IED, CIM) | O31: Students measure manufactured parts, calculate statistical variation (mean, standard deviation, upper/lower control limits), and plot Statistical Process Control (SPC) charts to evaluate manufacturing stability. | P31: Processing Information — Compiling, coding, categorizing, calculating, tabulating, auditing, or verifying information/data. | Q31: Analyze data to identify or resolve operational problems. | R31: Monitoring Processes, Materials, or Surroundings — Monitoring and reviewing information from materials/events to assess problems. | S31: Mathematics/Statistics — Apply math and statistical theory/methods; analyze development or manufacturing procedures.
A32: Recognize & respond to physical security & cybersecurity risks | B32: Safety, Security & Compliance | C32: NA | D32: NA | E32: NA | F32: Standard 11.0 | G32: Standard 11.0 “Analyze Physical Security and Cybersecurity Threats” (11.1-11.7) is a dedicated standard on this exact topic. | H32: CIS270 / ITS110 | I32: “Identify perpetrators, their resources, and their motivations in cyberspace; apply risk analysis methodologies to identify potential vulnerabilities, associated impacts, and recommend appropriate responses.” | J32: ECE 578 | K32: Examines risk mitigation strategies, physical and network security, operational technology (OT) protocols, and threat vectors in automated industrial environments. | L32: CP-101 / CIS-110 | M32: Identifies physical facility access threats, applies AAA/CIA security frameworks, recognizes OT network vulnerabilities, and adheres to cybersecurity protocols in fab environments. | N32: PLTW Computer Science (SEC) | O32: Students analyze physical and digital access controls, simulate network threat response, evaluate CIA triad enforcement, and establish system defense protocols. | P32: Review existing electrical engineering criteria to identify necessary revisions, deletions, or amendments. | Q32: Implement security measures for computer or information systems; analyze security of systems, network, or data. | R32: Inspect mechanical equipment to locate damage, defects, or wear. | S32: Perform risk assessments and execute tests of data processing systems to ensure functioning of security measures.
A33: Follow OSHA, COHE, & cleanroom safety protocols | B33: Safety, Security & Compliance | C33: NA | D33: NA | E33: NA | F33: 2.1; 2.8 | G33: 2.1: “Comply with...OSHA...and COHE (Control of Hazardous Energy).” 2.8 covers cleanroom protocol and housekeeping. | H33: MNT201 | I33: Covers safety procedures and equipment used in the semiconductor and nanotechnology industries. Emphasizes chemical, biological, and energy safety protocols, environmental health and safety (EHS) compliance, infrastructure facility safety, and proper operation within cleanroom environments. | J33: MSE / ECE / CHEE 515: | K33: Focuses on hazardous material management, chemical safety, cleanroom environmental protocols, waste minimization, and compliance with industry safety standards. | L33: CP-101 / AIT-101 | M33: Complies with OSHA safety regulations, executes Control of Hazardous Energy (COHE/LOTO) procedures, and maintains cleanroom contamination control standards. | N33: PLTW Engineering (CIM, POE) | O33: Students practice industrial safety protocols, including Lockout/Tagout (LOTO) simulations, hazard evaluation, proper PPE usage, and aseptic/clean environment practices. | P33: Review, develop, or prepare maintenance and operating standards. | Q33: Develop plans to safeguard computer files and meet emergency data processing needs. | R33: Perform work involving safety standards to keep machines, mechanical equipment, or structures in repair. | S33: Evaluating Information to Determine Compliance with Standards — Determine whether processes comply with laws, regulations, or standards.
A34: Diagnose issues in semiconductor tools & systems | B34: Equipment, Systems & Automation | C34: NA | D34: NA | E34: NA | F34: 5.12; 6.8-6.10 | G34: 5.12: troubleshoot piping, pumps, valves, pneumatic/hydraulic systems, heat exchangers; 6.8-6.10 cover a systematic diagnostic process for electrical failures. | H34: AIT132 | I34: "Apply knowledge of basic semiconductor manufacturing concepts and processes, basic industrial electrical principles, schematics, circuits, hand tools, and appropriate problem-solving models to troubleshoot and address problems [diagnose issues] in the semiconductor industry."\n\n*"Apply knowledge of vacuum components, procedures, theory, and hand tools to efficiently and effectively troubleshoot common issues found in a system under vacuum."* | J34: MSE / ECE 547L: | K34: Provides hands-on cleanroom training on unit operations, tool calibration, equipment diagnostics, and failure analysis for processing hardware. | L34: CP-104 / AIT-215 | M34: Uses systematic diagnostic procedures, multi-meter measurements, and software diagnostic tools to troubleshoot electrical, mechanical, pneumatic, and vacuum tool failures. | N34: PLTW Engineering (POE, DE, CIM) | O34: Students apply systematic root-cause analysis to locate and resolve faults in electrical circuits, pneumatic systems, mechanical drives, and automated code. | P34: Set up and operate specialized or standard test equipment to diagnose, test, or analyze performance. | Q34: Test computer software or hardware, using standard diagnostic testing equipment and procedures. | R34: Inspect, operate, or test machinery or equipment to diagnose machine malfunctions; troubleshoot system problems. | S34: Conduct analyses addressing issues such as failure, reliability, or yield improvement; test performance of integrated systems.
A35: Operate automated tools & robotics | B35: Equipment, Systems & Automation | C35: NA | D35: NA | E35: NA | F35: 7.11; 2.5 | G35: 7.11 describes automated/robotic systems moving materials and operating equipment; 2.5 covers safety procedures for automated/robotic systems. | H35: AIT270 | I35: "Fundamental principles of working safely with robots, and applications and trends in industrial robotics. Includes types of robots, axes and coordinate systems, programming and operating robots. Incorporates end effectors and collaborative robots." | J35: SIE 454 / 554 | K35: Covers automated tooling systems, programmable logic controllers (PLCs), robotic integration, sensor networks, and automated feedback control in production. | L35: CP-102 / AIT-220 | M35: Configures, tests, and safely operates automated wafer handling systems, robotic pick-and-place arms, and programmable logic controller (PLC) cell interfaces. | N35: PLTW Engineering (CIM, POE) | O35: Students program, calibrate, and operate automated robotic workcells, G-code CNC machines, automated material handling systems, and programmable logic controller (PLC) sensor networks. | P35: Install or maintain electrical control systems, industrial automation systems, variable speed drives, or PLCs. | Q35: Test computer system operations to ensure proper functioning. | R35: Set up and operate machine tools to repair or fabricate machine parts, jigs, fixtures, or tools. | S35: Oversee operation of MEMS fabrication or assembly equipment; design engineering systems for automation of industrial tasks.
A36: Apply QA/QC procedures in production | B36: Manufacturing Processes & Quality | C36: NA | D36: NA | E36: NA | F36: 3.6-3.7 | G36: 3.6 covers quality assurance processes; 3.7 covers quality control and change management processes (SOPs, SPC, traceability). | H36: MNT235 | I36: "Analyze quality control methods including statistical process control (SPC) through the use of metrology techniques and tools to support quality in semiconductor manufacturing operations." | J36: SIE 506 | K36: Details Quality Assurance and Quality Control (QA/QC) methodologies, Six Sigma frameworks, ISO standards, total quality management, and inspection protocols. | L36: CP-103 / MET-210 | M36: Executes Quality Assurance (QA) and Quality Control (QC) inspection routines, enforces Standard Operating Procedures (SOPs), and logs traceability metrics. | N36: PLTW Engineering (IED, CIM) | O36: Students perform part dimensional verification using calipers/micrometers, implement SOPs, document quality control audits, and execute non-conformance logging. | P36: Direct quality control activities; evaluate designs or specifications to ensure quality. | Q36: Test computer system operations and software performance to ensure proper functioning. | R36: Inspect mechanical equipment to locate defects; test mechanical equipment to ensure proper functioning. | S36: Develop or validate product-specific test protocols, acceptance thresholds, or inspection tools for quality control testing.
A37: Monitor yield & identify factors affecting output | B37: Manufacturing Processes & Quality | C37: NA | D37: NA | E37: NA | F37: 3.4 | G37: 3.4: “Explain manufacturing yield, including the stages of yield loss and factors affecting yield, final test yield, and yield reliability.” | H37: MNT108 | I37: Focuses on statistical methods, quality control monitoring, run charts, and identifying variation factors to maintain target yield limits and optimize manufacturing output. | J37: MSE / ECE 546 | K37: Focuses on integrated process integration, yield limiting defects, failure modes in device fabrication, and root-cause analysis for output optimization. | L37: CP-103 / SMI-101 | M37: Tracks fabrication yield percentages, analyzes defect density sources, evaluates scrap rate causes, and reports factors impacting final product throughput. | N37: PLTW Engineering (CIM, EDD) | O37: Students calculate production yield metrics, track defect density across manufacturing runs, perform root-cause failure analyses, and adjust parameters to reduce scrap rate. | P37: Interpret test information to resolve design-related problems; resolve operational performance problems. | Q37: Monitor the performance of computer networks; analyze data to resolve operational problems. | R37: Monitoring Processes, Materials, or Surroundings — Detect or assess operational problems. | S37: Conduct analyses addressing failure, reliability, or yield improvement; monitor/calibrate systems to maximize production efficiency.
A38: Monitor Basic Process Parameters | B38: Cross-Cutting | C38: NA | D38: NA | E38: NA | F38: 7.1; 8.6-8.7 | G38: 7.1 covers determining whether a process is operating normally or outside expected limits; 8.6-8.7 cover sensor feedback and observing trends outside expected limits. | H38: MNT115 | I38: Covers fundamental semiconductor fabrication steps—including oxidation, photolithography, deposition, and etching—and tracking critical baseline parameters during operations. | J38: MSE 546 | K38: Teaches control and monitoring of core fabrication parameters including thermal oxidation, thin-film deposition, photolithography exposure, and plasma etching rates. | L38: CP-102 / SMI-101 | M38: Reads, logs, and evaluates core manufacturing operational parameters such as chamber temperature, gas flow, pressure, vacuum levels, and RF power. | N38: PLTW Engineering (CIM, POE) | O38: Students use industrial sensors and data acquisition interfaces to continuously log, visualize, and analyze operational variables (e.g., pressure, temperature, flow rate). | P38: Maintain system logs or manuals to document testing or operation of equipment; maintain operational records. | Q38: Monitor the performance of computer networks; document network-related activities or tasks. | R38: Perform routine maintenance, such as inspecting drives/motors, checking fluid levels, or replacing filters. | S38: Monitor or calibrate automated systems, industrial control systems, or system components to maximize efficiency.
A39: Maintain cleanroom gowning & housekeeping | B39: Cross-Cutting | C39: NA | D39: NA | E39: NA | F39: 2.8 | G39: 2.8: “proper gowning and de-gowning, keeping work areas clean and organized, eliminating trip hazards, documenting issues and near misses.” | H39: MNT201 | I39: Covers cleanroom protocol and safety standards, including contamination control, personal protective equipment (PPE)/gowning procedures, and facility housekeeping. | J39: FASTLab Training: Cleanroom Operations & Protocols | K39: Offers hands-on instruction within the NanoFab & Processing Facility (NF&P) covering ISO cleanroom protocols, gowning procedures, particle control, and contamination prevention. | L39: CP-101 / AIT-101 | M39: Demonstrates proper cleanroom gowning and de-gowning techniques, follows particle minimization routines, and maintains strict cleanroom protocols and housekeeping. | N39: PLTW Biomedical Science (PBS, MI) | O39: Students execute gowning sequences, adhere to strict contamination control procedures, and maintain standardized, hazard-free workplace environments. | P39: Assemble, test, or maintain circuitry; maintain electronic equipment and clean work areas. | Q39: Maintain computer hardware and physical network equipment workspace. | R39: Perform general cleaning of buildings, properties, or specialized factory machinery. | S39: Oversee operation and physical upkeep of microelectromechanical systems (MEMS) fabrication or assembly equipment.
A41: Automation, Controls, & Sensor Technologies, ONET - 17-3023.00, CIP - 47.0105
A42: Apply control systems concepts | C42: Automation, Controls, & Sensor Technologies | D42: 17-3023.00 | E42: 47.0105 | F42: Standard 8.0; Standard 10.0 | G42: Standard 8.0 (sensor solutions) and Standard 10.0 (PLC functionality) together cover control systems concepts. | H42: AIT215 | I42: Focuses on principles of industrial control systems, covering feedback dynamics, continuous system behavior, and tuning methodology. | J42: ECE 441A / AME 455 | K42: Automatic Control / Control Systems Analysis: Covers dynamic system modeling, feedback control system characteristics, stability analysis, steady-state error analysis, and PID/state-feedback control design. | L42: CP-102 / AIT-125 | M42: Analyzes feedback control loops, system response time, proportional-integral-derivative (PID) tuning, and dynamic system behavior in automated manufacturing environments. | P42: Design, test, or maintain electrical control systems, industrial automation equipment, and variable speed drives.
A43: Interpret PLC & sensor logic | C43: Automation, Controls, & Sensor Technologies | D43: 17-3023.00 | E43: 47.0105 | F43: 10.1-10.5; Standard 8.0 | G43: 10.1-10.5 cover PLC definition, components, function, and troubleshooting; Standard 8.0 covers sensor types and logic. | H43: AIT210 | I43: Teaches reading, analyzing, and troubleshooting ladder logic diagrams and connected discrete/analog sensor inputs. | J43: CYBV 330 | K43: Introduction to Industrial Control System Security: Introduces the operation, ladder logic, state transitions, and logic interpretation of Programmable Logic Controllers (PLCs) in industrial control networks. | L43: CP-102 / AIT-125 | M43: Reads and interprets ladder logic diagrams, boolean expressions, state machines, and discrete/analog sensor signal paths within industrial control circuits. | P43: Read blueprints, wiring diagrams, schematic drawings, ladder logic, or engineering instructions for assembling and troubleshooting automation units.
A44: Apply basic scripting for automation tasks | C44: Automation, Controls, & Sensor Technologies | D44: 17-3023.00 | E44: 47.0105 | F44: 7.12 | G44: 7.12: “...view dashboards that show equipment status, read simple graphs showing trends, understand basic python scripting.” | H44: CIS156 | I44: Covers Python scripting basics used for automation workflows, data manipulation, and device scripting. | J44: ECE 101 / ECE 201 | K44: Computer Programming I & II: Focuses on fundamental programming constructs, algorithmic automation, basic scripting, control structures, and software logic implementation. | L44: CP-103 / DAT-110 | M44: Writes and executes structured scripts (e.g., Python, Structured Text) to automate recurring equipment tasks, parse process logs, and manage tool communication protocols. | P44: Write and execute computer code, scripts, or program sequences to automate system tasks, routine testing, and data collection.
A45: Validate failsafe shutdown behaviors | C45: Automation, Controls, & Sensor Technologies | D45: 17-3023.00 | E45: 47.0105 | F45: 2.6 | G45: 2.6: “Explain the ‘fail safe’ component integrated in robotic and automated systems (i.e., emergency shutdowns, interlocks, and sensor-based stops).” | H45: AIT100 | I45: Emphasizes critical safety protocols, emergency shutdown sequence procedures, and safe functional states. | J45: CYBV 330 / AME 463 | K45: ICS Security & Industrial Automation: Covers safety-instrumented systems, fault diagnostic states, system isolation, and verifying failsafe shutdown sequences for automated process equipment. | L45: CP-101 / AIT-101 | M45: Verifies emergency power-off (EPO) circuits, safety relay states, and automated system drop-outs to ensure tools power down safely during fault conditions. | P45: Test emergency shutdown systems, safety cutoffs, and fail-safe control routines to ensure proper operational response during fault conditions.
A46: Implement machine safeguarding & interlocks | C46: Automation, Controls, & Sensor Technologies | D46: 17-3023.00 | E46: 47.0105 | F46: 2.2; 2.5 | G46: 2.2 covers guarded areas and LOTO indicators; 2.5: “...respect interlocks and access controls, never bypass safety systems.” | H46: AIT100 | I46: Teaches physical machine guarding standards, safety lockout/tagout procedures, and basic electrical interlocks. | J46: MNE 426 / CYBV 330 | K46: Health and Safety in Industrial Operations / ICS: Covers hazard evaluation, physical machine protection, safety interlock configuration, and procedural compliance for industrial machinery. | L46: CP-101 / AIT-101 | M46: Configures physical safety barriers, light curtains, interlock switches, and hardware-level safety isolation to prevent operator access to hazardous motion zones. | P46: Inspect, install, and maintain safety interlocks, protective barriers, and light curtains to comply with machine safety regulations.
A47: Integrate robots | C47: Automation, Controls, & Sensor Technologies | D47: 17-3023.00 | E47: 47.0105 | F47: 7.11 | G47: 7.11 covers robotic/automated systems moving materials generally, but conveyors and control-system integration are not explicitly named. | H47: AIT270 | I47: Focuses on industrial robotics setup, end-effector control, teaching position points, and cell integration. | J47: AME 551 | K47: Introductory Robotics: Kinematics, Dynamics, and Path Planning: Focuses on robot manipulator kinematics, motion planning, trajectory generation, and robotic tool path integration. | L47: CP-102 / AIT-220 | M47: Programs 6-axis and SCARA robotic movements, calibrates pick-and-place end effectors, and integrates robotic arms with automated wafer handling equipment. | P47: Install, configure, program, and maintain industrial automation systems, PLCs, and robotic devices.
A48: Configure PLC I/O modules | C48: Automation, Controls, & Sensor Technologies | D48: 17-3023.00 | E48: 47.0105 | F48: 10.2; 10.5 | G48: 10.2: “Identify four main components of a PLC (...input/output modules).” 10.5: “Use a PLC to troubleshoot input/out AC and DC modules.” | H48: AIT210 | I48: Hands-on instruction in wiring, assigning addresses, and setting up digital/analog I/O expansion cards on PLC racks. | J48: CYBV 330 / ECE 372A | K48: ICS Security / Microprocessor Organization: Teaches digital and analog I/O configuration, memory mapping, interrupt handling, and sensor/actuator hardware interfacing. | L48: CP-102 / AIT-125 | M48: Installs, wires, and addresses discrete and analog input/output (I/O) expansion cards, Fieldbus nodes, and Ethernet/IP modules on Programmable Logic Controllers. | P48: Connect, assign, and test digital and analog input/output (I/O) field modules and hardware interfaces on programmable controllers.
A49: Validate sensor-based control performance | C49: Automation, Controls, & Sensor Technologies | D49: 17-3023.00 | E49: 47.0105 | F49: 8.6-8.7 | G49: 8.6 covers configuring/operating an automated system using sensor feedback; 8.7 covers observing trends outside expected performance limits. | H49: AIT215 | I49: Covers open- and closed-loop continuous performance testing using live sensor feedback signals. | J49: ECE 442 | K49: Digital Control Systems: Explores discrete-time signal processing, A/D and D/A conversion, sensor sampling rate effects, closed-loop transient response, and performance validation. | L49: CP-102 / AIT-125 | M49: Tests closed-loop feedback responses, measures sensor hysteresis and response latency, and confirms automated system adjustments maintain target setpoints. | P49: Set up and operate specialized or standard test equipment to evaluate sensor feedback and verify system performance against specifications.
A50: Control loop theory | B50: Technical Foundations | C50: Automation, Controls, and Sensor Technologies | H50: ELC210 / MET220 | I50: Introduces open-loop vs. closed-loop systems, feedback mechanisms, and PID controller principles. | J50: ECE 441A | K50: Automatic Control: Focuses on open- and closed-loop feedback systems, transfer functions, frequency response (Bode plots), root locus techniques, and PID loop design. | L50: CP-102 / AIT-125 | M50: Evaluates open-loop and closed-loop control system models, dead time compensation, and PID controller gain adjustments to maintain setpoint stability. | P50: Analyze feedback signals and adjust operational parameters (such as PID settings) to maintain system stability and response accuracy.
A51: Sensor calibration principles | B51: Technical Foundations | C51: Automation, Controls, and Sensor Technologies | H51: ELC210 / MET220 | I51: Covers calibration protocols for temperature, pressure, flow rate, and proximity sensors. | J51: MSE / ECE 547L | K51: Semiconductor Processing Lab: Involves physical and chemical wafer process metrology, parameter verification, and sensor setup across lithography, etching, and thermal deposition equipment. | L51: CP-104 / MET-210 | M51: Performs multi-point calibrations, drift corrections, zero/span adjustments, and reference comparisons on industrial temperature, pressure, and flow sensors. | P51: Calibrate electronic instruments, temperature/pressure/position sensors, and measurement transducers according to technical manuals.
A52: SCADA alarm analytics | B52: Data, Analysis, & Digital Tools | C52: Automation, Controls, and Sensor Technologies | H52: ELC210 / MET220 | I52: Evaluates alarm frequency, nuisance alarms, and threshold triggers in SCADA supervisory logs. | J52: CYBV 330 / SIE 506 | K52: ICS Security / Quality Engineering: Covers SCADA alarm monitoring, fault log telemetry analysis, root-cause diagnostics, and statistical process control in automated plants. | L52: CP-103 / DAT-110 | M52: Analyzes Supervisory Control and Data Acquisition (SCADA) historical alarm logs, event rates, and fault severity distributions to optimize system alerts and minimize alarm fatigue. | P52: Monitor and evaluate system operational status, alarm logs, and fault data to identify root causes of equipment outages or performance degradation.
A53: HMI telemetry visualization | B53: Data, Analysis, & Digital Tools | C53: Automation, Controls, and Sensor Technologies | H53: ELC210 / MET220 | I53: Builds Human-Machine Interface (HMI) dashboards displaying real-time pressure, flow, and temp gauges. | J53: CYBV 330 / ECE 372A | K53: ICS Security / Microprocessor Organization: Demonstrates human-machine interface (HMI) screen mapping, real-time sensor data streaming visualization, and status indicator dashboards. | L53: CP-102 / AIT-125 | M53: Designs and modifies Human-Machine Interface (HMI) dashboards, real-time trend graphs, tool status displays, and telemetry indicators for equipment operators. | P53: Maintain, update, or operate human-machine interface (HMI) screen graphics and visual display telemetry for monitoring real-time system metrics.
A54: ISO 13849 safety circuit validation | B54: Safety, Security & Compliance | C54: Automation, Controls, and Sensor Technologies | H54: MET220 / ELC210 | I54: Tests redundant safety interlock loops, safety relays, and dual-channel stop circuits. | J54: SIE 508 / CYBV 330 | K54: Reliability Engineering / ICS Security: Explores functional safety standards, fail-safe architecture verification, risk assessment methodologies, and performance level safety validation. | L54: CP-101 / AIT-101 | M54: Audits and validates functional safety performance levels (PL a-e) and dual-channel safety relay loops according to ISO 13849 safety of machinery standards. | P54: Evaluate safety-related parts of control systems (SRP/CS) and review equipment designs to ensure compliance with international safety standards and performance levels.
A55: Fail-safe interlock testing | B55: Safety, Security & Compliance | C55: Automation, Controls, and Sensor Technologies | H55: MET220 / ELC210 | I55: Validates tool emergency shutdown (EMO) triggers, pressure relieve valves, and sensor trips. | J55: CYBV 330 / SIE 508 | K55: ICS Security & Reliability: Examines safety loop verification, emergency trip testing, failure-mode testing, and hardware/software safety interlocks. | L55: CP-101 / AIT-101 | M55: Systematically triggers tool interlocks, vacuum door switches, and gas isolation valves to verify hardware and software fail-safe state transitions. | P55: Execute functional safety testing on interlock circuits, trip switches, and emergency stops to verify fail-safe protection.
A56: SCADA system programming | B56: Equipment, Systems & Automation | C56: Automation, Controls, and Sensor Technologies | H56: ELC210 / MET220 | I56: Programs Supervisory Control and Data Acquisition (SCADA) tag databases, alarms, and controls. | J56: CYBV 330 | K56: Introduction to Industrial Control System Security: Covers SCADA architecture, field device telemetry collection, master terminal unit (MTU) communications, and operational software setup. | L56: CP-102 / AIT-125 | M56: Develops SCADA database tags, sets up remote terminal unit (RTU) polling loops, and builds real-time graphical control environments for industrial processes. | P56: Program and integrate Supervisory Control and Data Acquisition (SCADA) software, system communications, and centralized database reporting.
A57: Programmable logic controller integration | B57: Equipment, Systems & Automation | C57: Automation, Controls, and Sensor Technologies | H57: ELC210 | I57: Integrates PLCs with field devices, fieldbus networks, human-machine interfaces, and safety relays. | J57: CYBV 330 | K57: Introduction to Industrial Control System Security: Focuses on integrating PLCs into wider industrial automation networks, connecting field sensors, actuators, and communication protocols. | L57: CP-102 / AIT-125 | M57: Interfaces PLCs with variable frequency drives (VFDs), motor starters, field sensors, and higher-level Manufacturing Execution Systems (MES). | P57: Install, connect, and configure programmable logic controllers (PLCs) within industrial control panels and field equipment networks.
A58: PLC program modification | B58: Manufacturing Processes & Quality | C58: Automation, Controls, and Sensor Technologies | H58: ELC210 | I58: Teaches ladder logic modification, function blocks, timer/counter tuning, and PLC program updates. | J58: CYBV 330 | K58: Introduction to Industrial Control System Security: Details editing, debugging, and deploying updated ladder logic routines, timer/counter parameters, and control code on live or simulated controllers. | L58: CP-102 / AIT-125 | M58: Edits existing ladder logic routines, updates timer/counter presets, modifies safety logic rungs, and uploads/downloads verified program revisions. | P58: Modify PLC ladder logic, function blocks, and software code to adjust system operations, fix bugs, or optimize line efficiency.
A59: Sensor error diagnostics | B59: Manufacturing Processes & Quality | C59: Automation, Controls, and Sensor Technologies | H59: ELC210 / MET220 | I59: Identifies sensor signal drift, ground loops, wiring faults, and out-of-range sensor feedback. | J59: ECE 372A / SIE 508 | K59: Microprocessor Organization / Reliability Engineering: Focuses on signal fault isolation, out-of-range sensor error detection, noise filtering, and hardware interrupt-driven fault logging. | L59: CP-104 / AIT-215 | M59: Identifies open-circuit faults, signal noise, ground loops, out-of-range sensor drift, and wiring anomalies using multimeters and diagnostic software. | P59: Use multimeter, oscilloscope, and signal generator equipment to diagnose faulty sensors, broken wiring, and corrupted signal loops.
A61: Data/Cybersecurity/Infrastructure, ONET - 15-1231.00, CIP - 11.1003
A62: Apply AAA & CIA frameworks | B62: ? | E62: 11.1003 | F62: 11.2; 11.3 | G62: 11.2 explicitly names the “authentication, authorization and accounting (AAA)” framework; 11.3 explicitly names the “CIA Triad.” | H62: ITS110 | I62: Focuses on core cybersecurity principles, including identity verification, authorization models, and securing systems via Authentication, Authorization, Accounting (AAA) and Confidentiality, Integrity, and Availability (CIA) triad frameworks. | J62: ECE 509 / CYBV 301 | K62: Cyber Security – Concept, Theory, Practice / Fundamentals of Cybersecurity: Teaches core security models, focusing on Authentication, Authorization, Accounting (AAA) and the Confidentiality, Integrity, Availability (CIA) triad. | L62: CP-101 / CIS-110 | M62: Implements Authentication, Authorization, and Accounting protocols alongside Confidentiality, Integrity, and Availability principles to protect network access and data assets. | Q62: Implement security measures for computer or information systems; analyze system security to protect data confidentiality, integrity, and availability.
A63: Configure access controls on systems | B63: ? | C63: Data/Cybersecurity/Infrastructure | D63: 15-1231.00 | F63: 11.2 | G63: 11.2: the AAA framework is “used to manage network access, enforce policies, and monitor user activity.” | H63: ITS120 | I63: Teaches configuration of user privileges, file/directory permissions, group policies, and access control lists (ACLs) across industrial and corporate operating systems. | J63: ECE 524 / CYBV 326 | K63: Fundamentals of Cloud Security / Access Control & Identity Management: Covers system access policies, identity management architectures, role-based access control (RBAC), and enforcing boundary protection. | L63: CP-101 / CIS-110 | M63: Establishes role-based access control (RBAC), user privileges, and multi-factor authentication policies across fab manufacturing networks and control software. | Q63: Establish user accounts, set access permissions, manage security credentials, and configure system security parameters.
A64: Support quality audits | B64: ? | C64: Data/Cybersecurity/Infrastructure | F64: 9.8 | G64: 9.8 covers quality inspection processes and audits. | H64: MNT235 | I64: Covers quality assurance methodologies, measurement systems analysis, compliance standard evaluation, and audit procedures for semiconductor fabrication environments. | J64: SIE 567 / SIE 530 | K64: Reliability Engineering / Engineering Quality Control: Focuses on failure analysis, process variation, continuous quality control, and standard compliance frameworks across complex industrial and microelectronics systems. | L64: CP-103 / MET-210 | M64: Prepares compliance documentation, verifies standard operating procedures (SOPs), tracks calibration logs, and assists internal/external Quality Management System (QMS) auditors. | Q64: Audit network security, evaluate system performance logs, and inspect operational infrastructure to ensure compliance with technology standards.
A65: Monitor data integrity | B65: ? | C65: Data/Cybersecurity/Infrastructure | D65: 15-1231.00 | E65: 11.1003 | F65: 11.3 | G65: 11.3 covers “integrity” as one of the three CIA Triad principles. | H65: MNT108 | I65: Details real-time statistical tracking, control charting, data collection accuracy, and identifying out-of-spec process drifts to ensure chip manufacturing data integrity. | J65: SFWE 501 / ECE 519 | K65: Software Assurance & Security / Advanced Computer Security with ML: Details protocols for validating data feeds, establishing cryptographic hashing/attestation, and detecting unauthorized alterations in pipeline environments. | L65: CP-103 / DAT-110 | M65: Tracks data validation checks, error logs, and checksums to ensure telemetry, yield metrics, and equipment logs remain accurate and untampered with. | Q65: Monitor network operations and backup processes to ensure continuous data accuracy, prevent corruption, and maintain recovery procedures.
A66: Database design principles | B66: Technical Foundations | C66: Data/Cybersecurity/Infrastructure | H66: CIS105 / BPC110 | I66: Introduces relational database schemas, data normalization, and structured tables for manufacturing data. | J66: MIS 502 / MIS 531 | K66: Database Management Systems / Enterprise Data Management: Covers relational database conceptual design, normalization, schema structures, and entity-relationship modeling for operational environments. | L66: CP-103 / DAT-110 | M66: Designs normalized relational database schemas, tables, primary/foreign key relationships, and data indexes to efficiently store manufacturing execution data. | Q66: Structure data stores and analyze data requirements to support network reporting, system logs, and operational asset management.
A67: OT cybersecurity threat hunting | B67: Data, Analysis, & Digital Tools | C67: Data/Cybersecurity/Infrastructure | H67: CIS114DE / ITS110 | I67: Inspects industrial network packet captures (PCAP) and SIEM logs for anomalous OT traffic. | J67: ECE 571 / CYBV 435 | K67: Fundamentals of Info & Network Security / Cyber Threat Intelligence: Focuses on network behavior analysis, signature and anomaly detection, and active threat hunting techniques applicable to industrial control/OT networks. | L67: CP-101 / CIS-190 | M67: Proactively searches Operational Technology (OT) networks for anomaly indicators, unauthorized network traffic, and malware targeting industrial control systems. | Q67: Analyze network traffic and security incident logs to proactively identify unauthorized access attempt patterns and operational technology threats.
A68: Fab database SQL querying | B68: Data, Analysis, & Digital Tools | C68: Data/Cybersecurity/Infrastructure | H68: CIS105 / BPC110 | I68: Writes SQL queries to extract lot history, yield reports, and tool downtime records from SQL databases. | J68: MIS 502 / ISTA 322 | K68: Database Management Systems / Data Bases and Web Systems: Teaches SQL/PL-SQL syntax, complex relational queries, data extraction, and structured database management. | L68: CP-103 / DAT-110 | M68: Writes structured SQL queries (SELECT, JOIN, GROUP BY) to extract, filter, and analyze equipment status and production yield metrics from fab databases. | Q68: Run database queries and command scripts to retrieve operational logs, system diagnostics, and network activity records.
A69: Fab cyber threat monitoring | B69: Safety, Security & Compliance | C69: Data/Cybersecurity/Infrastructure | H69: CIS114DE / ITS110 | I69: Monitors OT network traffic for anomalous intrusions, malware, and unauthorized access attempts. | J69: ECE 519 / SFWE 502 | K69: Advanced Computer Security with ML / Software DevSecOps: Instructs on automated monitoring of operational pipelines, real-time intrusion detection, and anomaly classification using automated tools and machine learning models. | L69: CP-101 / CIS-190 | M69: Utilizes Security Information and Event Management (SIEM) tools to monitor real-time security alerts and network traffic on shop-floor fab systems. | Q69: Monitor security alerts, intrusion detection logs, and system traffic in real time to prevent unauthorized access and cyber breaches.
A70: Securing legacy equipment endpoints | B70: Safety, Security & Compliance | C70: Data/Cybersecurity/Infrastructure | H70: CIS114DE / ITS110 | I70: Hardens legacy tool controllers (e.g., Windows XP/7/2000 nodes) with VLAN segmentation. | J70: ECE 576B / CYBV 470 | K70: Embedded System Design & Optimization / Industrial Control Systems Security: Details techniques for hard-wiring, patch isolation, physical/logical access controls, and boundary protection on non-upgradable legacy embedded controllers. | L70: CP-101 / CIS-190 | M70: Applies network isolation, VLAN segmentation, port security, and legacy OS hardening to protect older fab machinery lacking modern patch support. | Q70: Apply patch management, network isolation protocols, and security configurations to protect legacy OS endpoints and legacy hardware devices.
A71: Edge computing deployment | B71: Equipment, Systems & Automation | C71: Data/Cybersecurity/Infrastructure | H71: CIS114DE / ITS110 | I71: Configures local edge gateways on tool sub-panels for low-latency telemetry processing. | J71: ECE 513 / ECE 569 | K71: Web Development & IoT / High Performance Computing: Focuses on architecture, compute offloading, real-time sensor processing, and edge device integration in internet-of-things contexts. | L71: CP-103 / DAT-110 | M71: Deploys local edge gateway devices near fab tools to process real-time sensor streams and perform low-latency calculations before cloud/server sync. | Q71: Install, test, and maintain distributed local hardware, peripheral interfaces, and edge network devices across production areas.
A72: MES server integration | B72: Equipment, Systems & Automation | C72: Data/Cybersecurity/Infrastructure | H72: CIS105 / BPC110 | I72: Connects tool controllers with Manufacturing Execution System (MES) servers via SECS/GEM protocols. | J72: SIE 554A / ECE 573 | K72: Systems Engineering Process / Software Engineering Concepts: Examines enterprise system architectures, Manufacturing Execution System (MES) workflows, interfaces, and system-level API integration. | L72: CP-102 / AIT-125 | M72: Configures interface protocols (e.g., SECS/GEM, OPC UA) to link tool-level PLCs and controllers directly with Manufacturing Execution System (MES) servers. | Q72: Install, configure, and connect server hardware, specialized operating software, and system interfaces to integrate manufacturing systems with IT networks.
A73: Data pipeline monitoring | B73: Manufacturing Processes & Quality | C73: Data/Cybersecurity/Infrastructure | H73: CIS122 / BPC110 | I73: Verifies continuous data flow from tool sensors through edge brokers to manufacturing execution databases. | J73: ECE 523 / MIS 545 | K73: Engineering Applications of ML & Data Analytics / Data Mining & Data Warehousing: Covers continuous ETL (Extract, Transform, Load) pipelines, real-time stream validation, processing metrics, and automated logging infrastructure. | L73: CP-103 / DAT-110 | M73: Tracks automated data ingestion pipelines, verifies ETL job completions, and diagnoses data transfer bottlenecks between tool logs and central databases. | Q73: Track and evaluate data transmission across local and wide area networks to identify latency, connection drops, or transmission bottlenecks.
A74: Process telemetry analysis | B74: Manufacturing Processes & Quality | C74: Data/Cybersecurity/Infrastructure | H74: DAT110 / MET210 | I74: Evaluates real-time process sensor streams (gas flows, RF power, chamber pressures) for drift. | J74: ECE 546 / ECE 517 | K74: Semiconductor Processing / Measurement & Data Analysis: Covers real-time process monitoring, sensor telemetry aggregation, etching/deposition tool data analysis, and microelectronics process control. | L74: CP-103 / DAT-110 | M74: Analyzes continuous time-series process data (temperature, pressure, power levels) to identify process drift, thermal spikes, and cycle anomalies. | Q74: Analyze network performance statistics, telemetry logs, and diagnostic data to troubleshoot operational errors and optimize traffic flow.
A75: OT network topology | B75: Technical Foundations | C75: Semiconductor Data/Cybersecurity/Infrastructure | H75: CIS114DE / ITS110 | I75: Teaches Operational Technology (OT) network architectures, Purdue Model layers, and fab network routing. | J75: ECE 578 / ECE 512 | K75: Fundamentals of Computer Networks / Wireless & Ad Hoc Networks: Examines industrial network architectures, physical layout designs, bus topologies, fieldbus networks, and segmented network zones. | L75: CP-101 / CIS-190 | M75: Maps and manages industrial network architectures, including Purdue Model levels, air-gapped subnets, fieldbus loops, and managed industrial switch layouts. | Q75: Document, lay out, and maintain physical and logical network architecture diagrams, VLANs, and subnets connecting operational hardware.
A77: Equipment & Systems Maintenance, ONET - 49-9071.00, CIP - 46.0401
A78: Use diagnostics software | B78: ? | F78: 7.12 | G78: 7.12 covers general software tools (dashboards, equipment status, basic scripting) | H78: AIT210 | I78: Covers industrial diagnostics software skills, including basic Human Machine Interface (HMI) navigation, connecting online to a PLC, downloading programs, and using software to troubleshoot connected automated components and system faults. | J78: ECE 446 / MSE 446 | K78: Semiconductor Processing: Covers tool-level diagnostic systems, modern engineering diagnostic software, and process verification techniques used across fab units. | L78: CP-104 / AIT-215 | M78: Operates specialized equipment diagnostic utilities, error log viewers, and automated self-test software to isolate tool faults. | R78: Use diagnostic software, computerized testing tools, and system logs to troubleshoot and isolate machinery or facility equipment failures.
A79: Apply LOTO on equipment | B79: ? | C79: Equipment & Systems Maintenance | D79: 49-9071.00 | F79: 2.1 | G79: 2.1 explicitly names “lockout-tagout (LOTO) safety procedures.” | H79: AIT100 | I79: An introductory workplace safety course focusing on critical safety policies, procedures, hazardous energy control standards (Lockout/Tagout or LOTO), and proper usage of Personal Protective Equipment (PPE) to avoid industrial injuries. | J79: MSE 447L / ECE 547L | K79: Semiconductor Processing Lab: Conducted in the UA NanoFabrication Core Facility cleanroom, covering cleanroom protocol, equipment safety, and lockout/tagout (LOTO) procedures. | L79: CP-101 / AIT-101 | M79: Executes strict Lockout/Tagout (LOTO) energy control procedures to isolate electrical, pneumatic, chemical, and thermal power sources before servicing machinery. | R79: Perform lock-out/tag-out (LOTO) procedures on electrical, mechanical, and pneumatic energy sources prior to inspecting, servicing, or repairing equipment.
A80: Service pneumatic & hydraulic systems | B80: ? | C80: Equipment & Systems Maintenance | D80: 49-9071.00 | E80: 46.0401 | F80: Standard 5.0 | G80: Standard 5.0 (5.1-5.13) is entirely devoted to pneumatic/hydraulic systems, including 5.12: troubleshoot piping, pumps, valves, and components. | H80: AIT115 / AIT120 | I80: Dedicated fluid power modules designed for hands-on maintenance, analysis, circuit interpretation, and repair of pressurized liquid (hydraulic) and air-driven (pneumatic) industrial equipment. | J80: AME 455 | K80: Actuators and Controls in Manufacturing: Focuses on mechanical, pneumatic, and fluidic actuation systems used in automated industrial and semiconductor tool environments. | L80: CP-102 / AIT-120 | M80: Inspects, maintains, and repairs fluid power lines, valves, regulators, pumps, and pneumatic/hydraulic actuators used in tool automation. | R80: Inspect, repair, or replace pneumatic and hydraulic components, including valves, hoses, fluid lines, cylinders, and pressure regulators.
A81: Mechanical drive troubleshooting | B81: Technical Foundations | C81: Equipment and Systems Maintenance | H81: MET150 / MET215 | I81: Diagnoses mechanical drive components, gearboxes, motors, and belt assemblies in fab machinery. | J81: AME 352 | K81: Dynamics of Machines: Teaches force analysis, mechanical drive assemblies, gears, linkage mechanisms, and kinematic troubleshooting for mechanical systems. | L81: CP-102 / AIT-120 | M81: Diagnoses mechanical failure modes in belts, gearboxes, lead screws, bearings, and drive couplings across automated transport systems. | R81: Inspect mechanical equipment to locate defects or wear; diagnose and realign gears, belts, pulleys, shafts, and drive couplings.
A82: Vacuum pressure physics | B82: Technical Foundations | C82: Equipment and Systems Maintenance | H82: SEM101 / MET215 | I82: Teaches vacuum pressure regimes, roughing/turbomolecular pump behavior, and vacuum chamber dynamics. | J82: MSE 437 / CHEE 437 | K82: Surface Science: Covers gas/solid surface interactions, molecular flux, vacuum physics fundamentals, and low-pressure environment dynamics in chip manufacturing. | L82: CP-104 / SMI-101 | M82: Applies kinetic gas principles, mean free path calculations, and pressure regime concepts (rough, high, ultra-high vacuum) to chamber operations. | R82: Monitor and maintain vacuum systems and pressure differential controls; apply fluid/gas pressure principles to evaluate system seal integrity.
A83: Sensor diagnostic log interpretation | B83: Data, Analysis, & Digital Tools | C83: Equipment and Systems Maintenance | H83: MET215 / ELE211 | I83: Analyzes sub-system diagnostic logs to identify pre-failure trends in pumps, heaters, and valves. | J83: ECE 415 / CHEE 415 | K83: Process Control and Instrumentation: Focuses on sensor data processing, fault diagnosis, dynamic system feedback loops, and signal log interpretation for semiconductor tools. | L83: CP-104 / AIT-215 | M83: Parses raw time-stamped sensor log files to detect intermittent signal loss, out-of-spec readings, and pre-failure drift patterns. | R83: Review and interpret diagnostic logs, sensor telemetry reports, and fault codes to pinpoint root causes of operational malfunctions.
A84: Predictive maintenance software | B84: Data, Analysis, & Digital Tools | C84: Equipment and Systems Maintenance | H84: MET215 / MET210 | I84: Uses PdM software tools to track vibration, thermal signatures, and mean time between failures (MTBF). | J84: SIE 431 / ECE 431 | K84: Simulation Modeling and Process Improvement: Explores statistical process control (SPC), machine failure modeling, software prediction, and fault detection and classification (FDC). | L84: CP-103 / DAT-110 | M84: Utilizes condition monitoring software, vibration analysis tools, and trend algorithms to schedule proactive maintenance before tool failure occurs. | R84: Use Computerized Maintenance Management Systems (CMMS) and predictive maintenance software to track equipment wear, log repairs, and schedule routines.
A85: Chemical delivery system safety | B85: Safety, Security & Compliance | C85: Equipment and Systems Maintenance | H85: SEM101 / MET101 | I85: Performs safe chemical flush, valve manifold box isolation, and hazardous liquid transfer. | J85: CHEE 515 / MSE 515 | K85: Microelectronics Manufacturing and the Environment: Focuses on toxic gas/hazardous chemical handling, wet etching chemistry safety, liquid supply infrastructure, and environmental safeguards. | L85: CP-101 / EHS-105 | M85: Follows hazardous material protocols for safely operating and maintaining chemical cabinet distribution, purge routines, and double-containment piping. | R85: Inspect and maintain hazardous material lines, fluid delivery channels, and chemical systems following safety standards and containment protocols.
A86: High-voltage isolation protocol | B86: Safety, Security & Compliance | C86: Equipment and Systems Maintenance | H86: ELC115 / MET101 | I86: Implements electrical high-voltage isolation, grounding hooks, and arc flash safety protocols. | J86: ECE 351C | K86: Electronic Circuits and Power: Covers high-voltage/power electronics handling, electrical safety isolation techniques, and circuit protection protocols. | L86: CP-101 / ELC-101 | M86: Applies NFPA 70E safety practices to verify zero-energy states, ground high-voltage capacitors, and isolate RF generator power supplies. | R86: Execute electrical safety isolation, de-energization, and grounding protocols when inspecting or repairing high-voltage control systems and power units.
A87: Plasma etch system repair | B87: Equipment, Systems & Automation | C87: Equipment and Systems Maintenance | H87: SEM201 / MET215 | I87: Services plasma generation units, RF matching networks, showerhead assemblies, and chamber liners. | J87: MSE 447L / ECE 447L | K87: Semiconductor Processing Laboratory: Direct laboratory units on dry plasma etching equipment operation, tool parameter tuning, surface reactions, and process troubleshooting. | L87: CP-104 / AIT-215 | M87: Performs component replacement, RF matching adjustments, and process chamber maintenance on dry plasma etching equipment. | R87: Repair, overhaul, and reassemble complex industrial process machinery, specialized production equipment, and mechanical tools.
A88: Robotic arm calibration | B88: Equipment, Systems & Automation | C88: Equipment and Systems Maintenance | H88: MET180 / MET220 | I88: Calibrates end-effector teaching points, wafer pickup positioning, and multi-axis arm motion. | J88: AME 463 / ECE 463 | K88: Robotics & Industrial Automation: Covers kinematic modeling, motion planning, spatial calibration, and end-effector alignment for automated manufacturing arms. | L88: CP-102 / AIT-220 | M88: Teaches precise coordinate points, calibrates optical alignment sensors, and zeros encoder positions for wafer transfer arms. | R88: Align, adjust, and calibrate automated mechanical mechanisms, robotic end-effectors, actuators, and positional hardware.
A89: Vacuum pump overhaul | B89: Manufacturing Processes & Quality | C89: Equipment and Systems Maintenance | H89: MET215 | I89: Covers disassembly, rebuilding, sealing, and maintenance of dry vacuum pumps and turbopumps. | J89: MSE 447L / ECE 547L | K89: Semiconductor Processing Lab: Hands-on training inside the NanoFab facility with deposition and etch vacuum chamber pumping stacks (turbomolecular, roughing, and cryogenic pumps). | L89: CP-104 / AIT-215 | M89: Disassembles, cleans, replaces seals/vanes on turbomolecular and dry mechanical backing pumps, reassembling them to factory spec. | R89: Dismantle, repair, and rebuild mechanical vacuum pumps, motors, compressors, and auxiliary fluid-handling components.
A90: Chamber seal leak detection | B90: Manufacturing Processes & Quality | C90: Equipment and Systems Maintenance | H90: MET215 / SEM201 | I90: Conducts helium leak detection, vacuum pressure decay checks, and O-ring seal replacements. | J90: MSE 447L / ECE 447L | K90: Semiconductor Processing Laboratory: Hands-on cleanroom maintenance operations involving high-vacuum chamber sealing, helium mass spectrometer leak testing, and vacuum pressure integrity. | L90: CP-104 / AIT-215 | M90: Performs helium leak detection using mass spectrometry sniffer probes and vacuum decay rate checks on sealed process chambers. | R90: Conduct pressure-drop checks and leak testing on sealed process chambers, gas delivery lines, and containment units to locate defective gaskets or seals.
A92: Automation, Controls, & Sensor Technologies, ONET - 15-1231.00, CIP - 11.1003
A93: Use basic materials science concepts | B93: ? | C93: Manufacturing Operations | D93: 51-9141.00 | E93: 15.0616 | F93: 1.7; 3.1 | G93: 1.7 names “materials science” as foundational knowledge; 3.1 lists key materials (silicon wafers, photoresists, gases, deposits). | H93: MNT225 | I93: Material Properties and Effects of Size — Explores physical, chemical, and structural properties of materials, covering material behavior and science concepts applied in micro- and nano-scale manufacturing. | J93: MSE 240 / MSE 331R | K93: Provides core knowledge in atomic structure, phase diagrams, crystalline structures, and chemical kinetics applicable to silicon substrates and thin films. | L93: CP-101 / SMI-101 | M93: Evaluates atomic structure, bandgap theory, crystal orientation, and chemical/physical properties of semiconductor substrates (Si, GaAs, SiC). | Q93: Evaluate physical network media specifications, optical fiber characteristics, and cabling material limits under varying thermal and environmental conditions.
A94: Follow wafer flow steps | B94: ? | C94: Manufacturing Operations | D94: 51-9141.00 | E94: 15.0616 | F94: 4.4 | G94: 4.4: “Describe a typical wafer flow process (i.e., depositing a layer of material, photo masking a pattern, removing parts of the deposited material...).” | H94: MNT116 | I94: Semiconductor Manufacturing Processes, Tools and Techniques — Covers hands-on tool operations, step-by-step processing sequences, cleanroom safety, and end-to-end wafer flow in chip fabrication environments. | J94: ECE / MSE 546 | K94: Covers the end-to-end unit operations involved in microelectronic device fabrication, tracking wafer pathways through oxidation, photolithography, doping, etching, and metallization. | L94: CP-101 / SMI-101 | M94: Tracks sequential fab processing steps—including oxidation, photolithography, etch, ion implantation, deposition, and planarization—through the wafer line. | Q94: Follow sequential technical workflows, network maintenance schedules, and established standard operating procedures (SOPs) for IT updates.
A95: Semiconductor Manufacturing | B95: Semiconductor Manufacturing | C95: Manufacturing Operations | H95: MNT115 | I95: Semiconductor Manufacturing Processes (or AIT132 - Industrial Technology for the Semiconductor Industry) — Delivers a comprehensive overview of core manufacturing operations, substrate handling, equipment integration, and foundational industry fabrication techniques. | J95: ECE / MSE 546 | K95: The primary UArizona lecture course covering silicon/compound semiconductor fabrication theory, bulk crystal growth, integrated circuit manufacturing methodologies, and process integration. | L95: CP-101 / SMI-101 | M95: Applies foundational principles of front-end-of-line (FEOL) and back-end-of-line (BEOL) integrated circuit fabrication processes and cleanroom workflows. | Q95: Support specialized computer networks, server architecture, and IT infrastructure operating within automated industrial and manufacturing facilities.
A96: Wafer inspection techniques | B96: Technical Foundations | C96: Manufacturing Operations | H96: SEM101 / SEM110 | I96: Applies optical and inline metrology to inspect wafer surface defects and pattern fidelity. | J96: MSE / ECE 580 | K96: Focuses on metrology and analytical inspection methodologies (e.g., SEM, ellipsometry, optical microscopy, X-ray diffraction) used to inspect wafer defects and measure film thickness. | L96: CP-104 / MET-210 | M96: Performs optical, brightfield/darkfield, and automated defect inspection (ADI/AEI) to identify surface contamination, pattern bridges, and particulate defects. | Q96: Inspect physical network hardware, port connectivity, cable integrity, and server status lights to identify hardware faults or physical defects.
A97: Cleanroom protocol adherence | B97: Technical Foundations | C97: Manufacturing Operations | H97: SEM101 | I97: Enforces ISO cleanroom gowning, gown-room procedures, and contamination control protocols. | J97: MSE / ECE 547 (FASTLab Protocol) | K97: Provides hands-on training inside university cleanrooms (NanoFab / FASTLab), covering gowning protocols, contamination control, particle prevention, and safety standards. | L97: CP-101 / AIT-101 | M97: Maintains ISO class cleanroom standards through strict gowning procedures, particle counter monitoring, pressure differential checks, and contamination controls. | Q97: Maintain physical network equipment workspaces, data centers, and server rooms according to facility access and environmental control standards.
A98: Manufacturing execution system logging | B98: Data, Analysis, & Digital Tools | C98: Manufacturing Operations | H98: SEM101 / BPC110 | I98: Records wafer lot moves, track recipe IDs, split logs, and operator holds in MES software. | J98: SIE 462 / SIE 562 | K98: Focuses on factory operations, shop-floor management, batch tracking, and inventory control systems applicable to MES logging and wafer lot tracking. | L98: CP-103 / DAT-110 | M98: Logs real-time batch records, equipment states, lot moves, and process parameters into Manufacturing Execution System (MES) client interfaces. | Q98: Document network support activities, log technical problems, and record maintenance actions in system databases and ticketing tools.
A99: Equipment run log parsing | B99: Data, Analysis, & Digital Tools | C99: Manufacturing Operations | H99: CIS122 / BPC110 | I99: Extracts tool event timestamps, wafer counts, and fault codes from flat text log files. | J99: ECE 479 / SIE 410A | K99: Teaches automated data ingestion, tool status log evaluation, and data processing techniques necessary for parsing diagnostic output from semiconductor fabrication tools. | L99: CP-103 / DAT-110 | M99: Extracts, formats, and analyzes time-stamped tool run logs to identify cycle time anomalies, process drift, and recipe abort triggers. | Q99: Read and analyze computer network diagnostic logs, error reports, and system traffic data to isolate and resolve operational problems.
A100: Pyrophoric gas safety | B100: Safety, Security & Compliance | C100: Manufacturing Operations | H100: SEM101 / MET101 | I100: Handles hazardous gas cabinets, double-containment piping, silane leak detection, and burn boxes. | J100: CHE / MSE 412 (or EHS Safety Modules) | K100: Covers industrial chemical hazards, hazardous gas delivery systems (silane, arsine, phosphine), upper/lower explosive limits, and chemical safety protocols required in fab environments. | L100: CP-101 / EHS-105 | M100: Executes safety protocols, gas cabinet purge routines, and emergency isolation procedures for reactive and self-igniting gases (e.g., silane, diborane). | Q100: Follow emergency plans, safety guidelines, and disaster recovery procedures to safeguard IT hardware and data processing infrastructure.
A101: Lockout/tagout execution | B101: Safety, Security & Compliance | C101: Manufacturing Operations | H101: SEM101 / MET101 | I101: Executes Lockout/Tagout (LOTO) procedures across electrical, pneumatic, and chemical supplies. | J101: ENGR 495A / EHS Tool Safety | K101: Covers zero-energy-state verification, industrial safety compliance (OSHA/SEMI S2 standards), electrical/pneumatic isolation, and tool safety procedures. | L101: CP-101 / AIT-101 | M101: Performs physical zero-energy state verification, applies personalized locks/tags, and logs LOTO documentation prior to equipment maintenance. | Q101: Execute power-down, equipment isolation, and safety protocols prior to servicing, replacing, or installing network hardware and power units.
A102: Automated material handling system operation | B102: Equipment, Systems & Automation | C102: Manufacturing Operations | H102: MET180 / MET220 | I102: Operates track-mounted Automated Material Handling Systems (AMHS) and inter-bay stockers. | J102: SIE 482 / SIE 582 | K102: Covers automated material handling systems (AMHS), robotic arm kinematics, overhead hoist transport (OHT) logic, and fab automation workflows. | L102: CP-102 / AIT-220 | M102: Monitors and controls automated overhead hoist transport (OHT) systems and track stockers responsible for wafer cassette transfers throughout the fab. | Q102: Monitor and support automated data backup systems, system monitoring software, and network hardware data transfer functions.
A103: FOUP loading and unloading | B103: Equipment, Systems & Automation | C103: Manufacturing Operations | H103: SEM101 / MET180 | I103: Manages Front Opening Unified Pod (FOUP) docking, purge valves, and wafer transfer interfaces. | J103: MSE / ECE 547 | K103: Practical lab training on wafer carrier handling, Front Opening Unified Pod (FOUP) interface operations, and manual/automated tool interface docks inside cleanroom facilities. | L103: CP-102 / SMI-101 | M103: Safely docks, locks, and interfaces Front Opening Universal Pods (FOUPs) with tool load ports to prevent particle ingress during wafer transfer. | Q103: Install, mount, swap, and position physical network hardware, rack-mounted switches, patch panels, and storage media devices.
A104: Photolithography execution | B104: Manufacturing Processes & Quality | C104: Manufacturing Operations | H104: SEM110 | I104: Covers photoresist coat, alignment, UV exposure, track develop, and critical dimension (CD) control. | J104: ECE / MSE 546 (Lab: MSE 547) | K104: Covers photoresist spin coating, soft/hard baking, optical exposure tool operations (steppers/aligners), pattern alignment, and development. | L104: CP-101 / SMI-101 | M104: Applies photoresist coating, performs softbake, operates alignment/exposure steppers/scanners, and executes chemical development and hardbake cycles. | Q104: Execute precise system software configuration, OS image deployments, and step-by-step technical setup protocols.
A105: Chemical mechanical planarization | B105: Manufacturing Processes & Quality | C105: Manufacturing Operations | H105: SEM110 / SEM210 | I105: Applies polishing slurry chemical dynamics, pad conditioning, and wafer planarization operations. | J105: ECE / MSE 546 | K105: Covers chemical-mechanical planarization (CMP) fundamentals, slurry dynamics, pad conditioning, and inter-layer dielectric (ILD) / metal polishing operations. | L105: CP-101 / SMI-101 | M105: Controls slurry flow rates, pad polishing pressure, and endpoint detection during Chemical Mechanical Planarization (CMP) to achieve global wafer flatness. | Q105: Perform routine physical maintenance, cleaning, and preparation of server racks, network equipment chassis, and interface ports.
...
